集積回路工学/8bitCPU/src/dut.v
// Data Memory
module dm(dout, addr, BUS, LD, CK);
	output [7:0] dout;
	input [7:0] addr, BUS;
	input LD;
	input CK;
	reg [7:0] mem [0:255];
	integer i;

	initial begin
		for(i =0; i < 256; i = i + 1)
			mem[i] <= 8'd0;
	end

	always @(posedge CK) begin
		if(LD) begin
			mem[addr] <= BUS;
		end
	end

	assign dout = mem[addr];
endmodule




// Lookup Table (decoder)
module lut(LD, SEL, cFlag, OP);
	output [6:0] LD;
	output [2:0] SEL;
	input [4:0] OP;
	input cFlag;

	reg [9:0] mem [0:63];

	assign SEL = mem[{OP, cFlag}];
	assign LD = mem[{OP, cFlag}] >> 3;

	initial begin
		// 	   OP4-0   cFlag         LD6-0    SEL2-0
		mem[{5'b00000, 1'b0}] <= {7'b0000001, 3'b000};// ADD A, Im
		mem[{5'b00000, 1'b1}] <= {7'b0000001, 3'b000};
		mem[{5'b00001, 1'b0}] <= {7'b0000001, 3'b001};// MOV A, B + Im
		mem[{5'b00001, 1'b1}] <= {7'b0000001, 3'b001};
		mem[{5'b00010, 1'b0}] <= {7'b0000001, 3'b010};// IN A, in + Im
		mem[{5'b00010, 1'b1}] <= {7'b0000001, 3'b010};
		mem[{5'b00011, 1'b0}] <= {7'b0000001, 3'b011};// MOV A, Im
		mem[{5'b00011, 1'b1}] <= {7'b0000001, 3'b011};

		mem[{5'b00100, 1'b0}] <= {7'b0000010, 3'b000};// MOV B, A + Im
		mem[{5'b00100, 1'b1}] <= {7'b0000010, 3'b000};
		mem[{5'b00101, 1'b0}] <= {7'b0000010, 3'b001};// ADD B, Im
		mem[{5'b00101, 1'b1}] <= {7'b0000010, 3'b001};
		mem[{5'b00110, 1'b0}] <= {7'b0000010, 3'b010};// IN B, in + Im
		mem[{5'b00110, 1'b1}] <= {7'b0000010, 3'b010};
		mem[{5'b00111, 1'b0}] <= {7'b0000010, 3'b011};// MOV B, Im
		mem[{5'b00111, 1'b1}] <= {7'b0000010, 3'b011};

		mem[{5'b01000, 1'b0}] <= {7'b0000100, 3'b011};// MOV C, Im
		mem[{5'b01000, 1'b1}] <= {7'b0000100, 3'b011};
		mem[{5'b01001, 1'b0}] <= {7'b0001000, 3'b000};// MOV R[C], A + Im
		mem[{5'b01001, 1'b1}] <= {7'b0001000, 3'b000};
		mem[{5'b01010, 1'b0}] <= {7'b0000001, 3'b111};// MOV A, R[C]
		mem[{5'b01010, 1'b1}] <= {7'b0000001, 3'b111};
		mem[{5'b01011, 1'b0}] <= {7'b0000001, 3'b100};// ADD A, R[C]
		mem[{5'b01011, 1'b1}] <= {7'b0000001, 3'b100};

		mem[{5'b01100, 1'b0}] <= {7'b0010000, 3'b001};// OUT B + Im
		mem[{5'b01100, 1'b1}] <= {7'b0010000, 3'b001};
		mem[{5'b01101, 1'b0}] <= {7'b0010000, 3'b011};// OUT Im
		mem[{5'b01101, 1'b1}] <= {7'b0010000, 3'b011};

		mem[{5'b01110, 1'b0}] <= {7'b1000000, 3'b011};// JNC Im (JMP)
		mem[{5'b01110, 1'b1}] <= {7'b0000000, 3'b000};// JNC Im (NOP)

		mem[{5'b01111, 1'b0}] <= {7'b1000000, 3'b011};// JMP Im
		mem[{5'b01111, 1'b1}] <= {7'b1000000, 3'b011};

		mem[{5'b10000, 1'b0}] <= {7'b0100000, 3'b011};// MOV D, Im
		mem[{5'b10000, 1'b1}] <= {7'b0100000, 3'b011};
	end
endmodule




module program_counter_8b(AD, CK, LD, ADR, EVENT, VEC);
	output [7:0] AD;
	input [7:0] ADR, VEC;
	input CK, EVENT;
	input LD;

	reg [7:0] Q;

	initial begin
		Q <= 8'd0;
	end

	always @(posedge CK or posedge EVENT) begin
		if(EVENT && VEC != 8'd0) begin
			Q <= VEC;
		end else begin
			Q <= (LD) ? ADR : Q + 8'd1;
		end
	end

	assign AD = Q;
endmodule




module register_8b(QOUT, CK, LD, BUS);
	output [7:0] QOUT;
	input [7:0] BUS;
	input CK, LD;

	reg [7:0] Q;

	initial begin
		Q <= 8'd0;
	end

	always @(posedge CK) begin
		if(LD) begin
			Q <= BUS;
		end
	end

	assign QOUT = Q;
endmodule




module registers(Aout, Bout, Cout, Dout, Oout, CK, LD, BUS);
	output [7:0] Aout, Bout, Cout, Dout, Oout;
	input [7:0] BUS;
	input [6:0] LD;
	input CK;

	register_8b Areg(Aout, CK, LD[0], BUS);
	register_8b Breg(Bout, CK, LD[1], BUS);
	register_8b Creg(Cout, CK, LD[2], BUS);
	register_8b Dreg(Dout, CK, LD[5], BUS);
	register_8b Oreg(Oout, CK, LD[4], BUS);
endmodule




module sel1(Y, SEL, C0, C1, C2, C3);
	output [7:0] Y;
	input [7:0] C0, C1, C2, C3;
	input [2:0] SEL;

	wire [1:0] select;

	assign select = SEL;
	assign Y = (select == 2'd0) ? C0 :
			   (select == 2'd1) ? C1 :
			   (select == 2'd2) ? C2 : C3;
endmodule




module sel2(Y, SEL, C0, C1);
	output [7:0] Y;
	input [7:0] C0, C1;
	input [2:0] SEL;

	assign Y = (SEL[2] == 1'b0) ? C0 : C1;
endmodule




module alu(BUS, cFlag, Y, IM);
	output [7:0] BUS;
	output cFlag;
	input [7:0] Y, IM;
	wire [8:0] ADD;

	assign ADD = Y + IM;
	assign BUS = ADD;// connect the last 8 bits
	assign cFlag = ADD[8];
endmodule




module dff(D, CK, QOUT);
	input D, CK;
	output QOUT;

	reg Q;

	initial begin
		Q <= 1'd0;
	end

	always @(posedge CK) begin
		Q <= D;
	end

	assign QOUT = Q;
endmodule

集積回路工学/8bitCPU/Q2/im.v
// Instruction Memory
module im(dout,
          addr);
    output [12:0] dout;
    input [7:0] addr;
    
    reg [12:0] mem [0:255];
    
    initial begin
        mem[8'd0] <= {5'b00111, 8'd0 };	// MOV B, 0;
        mem[8'd1] <= {5'b00110, 8'b11001110};	// IN B, in - 50;
        mem[8'd2] <= {5'b01100, 8'd0 };	// OUT B + 0;
        mem[8'd3] <= {5'b01111, 8'd1 };	// JMP 1;
    end
    
    assign dout = mem[addr];
endmodule

集積回路工学/8bitCPU/Q2/testbench.v
module testbench_cpu8;
	reg CK;
	wire [6:0] LD;
	wire [4:0] OP;
	wire signed [7:0] IM, Aout, Bout, Cout, Dout, Oout, BUS, Y, DMout, ALU_IN;
	wire [7:0] ADDR;
	wire [12:0] IMout;
	wire cFlag, Dcflag;
	wire [2:0] SEL;
	wire key_event;

	reg [7:0] in;

	initial begin
		$dumpfile("cpu.vcd");
		$dumpvars(0, testbench_cpu8);

		CK <= 0;
		in <= 0;

		#6
			in <= 20;
		#6
			in <= 40;
		#6
			in <= 60;
		#6
			in <= 80;
		#6
			in <= 100;
		#6
			in <= 110;
		#6
			in <= 90;
		#6
			in <= 70;
		#6
			in <= 50;
		#6
			in <= 30;
		#6
			in <= 20;
		#6
			in <= 35;
		#6
			in <= 45;
		#6
			in <= 55;
		#6
			in <= 50;

		#10
			$finish;
	end

	always #1
		CK <= ~CK;

	assign key_event = 1'b0;// keypad
	registers registers(Aout, Bout, Cout, Dout, Oout, CK, LD, BUS);
	sel1 selector1(Y, SEL, Aout, Bout, in, 8'd0);
	alu alu(BUS, cFlag, Y, ALU_IN);
	dm data_memory(DMout, Cout, BUS, LD[3], CK);
	lut lut(LD, SEL, Dcflag, OP);
	im instruction_memory(IMout, ADDR);
	assign IM = IMout;// neglect the top 5 bits (OP)
	assign OP = (IMout >> 8);
	sel2 selector2(ALU_IN, SEL, IM, DMout);
	dff dff(cFlag, CK, Dcflag);
	program_counter_8b program_counter(ADDR, CK, LD[6], BUS, key_event, Dout);
endmodule

集積回路工学/8bitCPU/Q2/cpu.vcd
$date
	Fri Jul  9 16:00:31 2021
$end
$version
	Icarus Verilog
$end
$timescale
	1s
$end
$scope module testbench_cpu8 $end
$var wire 1 ! key_event $end
$var wire 1 " cFlag $end
$var wire 8 # Y [7:0] $end
$var wire 3 $ SEL [2:0] $end
$var wire 8 % Oout [7:0] $end
$var wire 5 & OP [4:0] $end
$var wire 7 ' LD [6:0] $end
$var wire 13 ( IMout [12:0] $end
$var wire 8 ) IM [7:0] $end
$var wire 8 * Dout [7:0] $end
$var wire 1 + Dcflag $end
$var wire 8 , DMout [7:0] $end
$var wire 8 - Cout [7:0] $end
$var wire 8 . Bout [7:0] $end
$var wire 8 / BUS [7:0] $end
$var wire 8 0 Aout [7:0] $end
$var wire 8 1 ALU_IN [7:0] $end
$var wire 8 2 ADDR [7:0] $end
$var reg 1 3 CK $end
$var reg 8 4 in [7:0] $end
$scope module alu $end
$var wire 1 " cFlag $end
$var wire 8 5 Y [7:0] $end
$var wire 8 6 IM [7:0] $end
$var wire 8 7 BUS [7:0] $end
$var wire 9 8 ADD [8:0] $end
$upscope $end
$scope module data_memory $end
$var wire 8 9 BUS [7:0] $end
$var wire 1 3 CK $end
$var wire 1 : LD $end
$var wire 8 ; dout [7:0] $end
$var wire 8 < addr [7:0] $end
$var integer 32 = i [31:0] $end
$upscope $end
$scope module dff $end
$var wire 1 3 CK $end
$var wire 1 " D $end
$var wire 1 + QOUT $end
$var reg 1 + Q $end
$upscope $end
$scope module instruction_memory $end
$var wire 13 > dout [12:0] $end
$var wire 8 ? addr [7:0] $end
$upscope $end
$scope module lut $end
$var wire 5 @ OP [4:0] $end
$var wire 1 + cFlag $end
$var wire 3 A SEL [2:0] $end
$var wire 7 B LD [6:0] $end
$upscope $end
$scope module program_counter $end
$var wire 8 C ADR [7:0] $end
$var wire 1 3 CK $end
$var wire 1 ! EVENT $end
$var wire 1 D LD $end
$var wire 8 E VEC [7:0] $end
$var wire 8 F AD [7:0] $end
$var reg 8 G Q [7:0] $end
$upscope $end
$scope module registers $end
$var wire 8 H BUS [7:0] $end
$var wire 1 3 CK $end
$var wire 7 I LD [6:0] $end
$var wire 8 J Oout [7:0] $end
$var wire 8 K Dout [7:0] $end
$var wire 8 L Cout [7:0] $end
$var wire 8 M Bout [7:0] $end
$var wire 8 N Aout [7:0] $end
$scope module Areg $end
$var wire 8 O BUS [7:0] $end
$var wire 1 3 CK $end
$var wire 1 P LD $end
$var wire 8 Q QOUT [7:0] $end
$var reg 8 R Q [7:0] $end
$upscope $end
$scope module Breg $end
$var wire 8 S BUS [7:0] $end
$var wire 1 3 CK $end
$var wire 1 T LD $end
$var wire 8 U QOUT [7:0] $end
$var reg 8 V Q [7:0] $end
$upscope $end
$scope module Creg $end
$var wire 8 W BUS [7:0] $end
$var wire 1 3 CK $end
$var wire 1 X LD $end
$var wire 8 Y QOUT [7:0] $end
$var reg 8 Z Q [7:0] $end
$upscope $end
$scope module Dreg $end
$var wire 8 [ BUS [7:0] $end
$var wire 1 3 CK $end
$var wire 1 \ LD $end
$var wire 8 ] QOUT [7:0] $end
$var reg 8 ^ Q [7:0] $end
$upscope $end
$scope module Oreg $end
$var wire 8 _ BUS [7:0] $end
$var wire 1 3 CK $end
$var wire 1 ` LD $end
$var wire 8 a QOUT [7:0] $end
$var reg 8 b Q [7:0] $end
$upscope $end
$upscope $end
$scope module selector1 $end
$var wire 8 c C0 [7:0] $end
$var wire 8 d C1 [7:0] $end
$var wire 8 e C2 [7:0] $end
$var wire 8 f C3 [7:0] $end
$var wire 3 g SEL [2:0] $end
$var wire 2 h select [1:0] $end
$var wire 8 i Y [7:0] $end
$upscope $end
$scope module selector2 $end
$var wire 8 j C0 [7:0] $end
$var wire 8 k C1 [7:0] $end
$var wire 3 l SEL [2:0] $end
$var wire 8 m Y [7:0] $end
$upscope $end
$upscope $end
$enddefinitions $end
#0
$dumpvars
b0 m
b11 l
b0 k
b0 j
b0 i
b11 h
b11 g
b0 f
b0 e
b0 d
b0 c
b0 b
b0 a
0`
b0 _
b0 ^
b0 ]
0\
b0 [
b0 Z
b0 Y
0X
b0 W
b0 V
b0 U
1T
b0 S
b0 R
b0 Q
0P
b0 O
b0 N
b0 M
b0 L
b0 K
b0 J
b10 I
b0 H
b0 G
b0 F
b0 E
0D
b0 C
b10 B
b11 A
b111 @
b0 ?
b11100000000 >
b100000000 =
b0 <
b0 ;
0:
b0 9
b0 8
b0 7
b0 6
b0 5
b0 4
03
b0 2
b0 1
b0 0
b0 /
b0 .
b0 -
b0 ,
0+
b0 *
b0 )
b11100000000 (
b10 '
b111 &
b0 %
b11 $
b0 #
0"
0!
$end
#1
b10 h
b10 $
b10 A
b10 g
b10 l
b11001110 /
b11001110 7
b11001110 9
b11001110 C
b11001110 H
b11001110 O
b11001110 S
b11001110 W
b11001110 [
b11001110 _
b110 &
b110 @
b11001110 8
b11001110 1
b11001110 6
b11001110 m
b11001110 )
b11001110 j
b11011001110 (
b11011001110 >
b1 2
b1 ?
b1 F
b1 G
13
#2
03
#3
b11001110 #
b11001110 5
b11001110 i
0T
1`
b1 h
b10000 '
b10000 B
b10000 I
b1 $
b1 A
b1 g
b1 l
b11001110 /
b11001110 7
b11001110 9
b11001110 C
b11001110 H
b11001110 O
b11001110 S
b11001110 W
b11001110 [
b11001110 _
b1100 &
b1100 @
b11001110 8
b0 1
b0 6
b0 m
b0 )
b0 j
b11001110 .
b11001110 M
b11001110 U
b11001110 V
b11001110 d
b110000000000 (
b110000000000 >
b10 2
b10 ?
b10 F
b10 G
13
#4
03
#5
b0 #
b0 5
b0 i
0`
1D
b11 h
b1000000 '
b1000000 B
b1000000 I
b11 $
b11 A
b11 g
b11 l
b1 /
b1 7
b1 9
b1 C
b1 H
b1 O
b1 S
b1 W
b1 [
b1 _
b1111 &
b1111 @
b1 8
b1 1
b1 6
b1 m
b1 )
b1 j
b11001110 %
b11001110 J
b11001110 a
b11001110 b
b111100000001 (
b111100000001 >
b11 2
b11 ?
b11 F
b11 G
13
#6
03
b10100 4
b10100 e
#7
b10100 #
b10100 5
b10100 i
1T
0D
b10 h
b10 '
b10 B
b10 I
b10 $
b10 A
b10 g
b10 l
b11100010 /
b11100010 7
b11100010 9
b11100010 C
b11100010 H
b11100010 O
b11100010 S
b11100010 W
b11100010 [
b11100010 _
b110 &
b110 @
b11100010 8
b11001110 1
b11001110 6
b11001110 m
b11001110 )
b11001110 j
b11011001110 (
b11011001110 >
b1 2
b1 ?
b1 F
b1 G
13
#8
03
#9
b11100010 #
b11100010 5
b11100010 i
0T
1`
b1 h
b10000 '
b10000 B
b10000 I
b1 $
b1 A
b1 g
b1 l
b11100010 /
b11100010 7
b11100010 9
b11100010 C
b11100010 H
b11100010 O
b11100010 S
b11100010 W
b11100010 [
b11100010 _
b1100 &
b1100 @
b11100010 8
b0 1
b0 6
b0 m
b0 )
b0 j
b11100010 .
b11100010 M
b11100010 U
b11100010 V
b11100010 d
b110000000000 (
b110000000000 >
b10 2
b10 ?
b10 F
b10 G
13
#10
03
#11
b0 #
b0 5
b0 i
0`
1D
b11 h
b1000000 '
b1000000 B
b1000000 I
b11 $
b11 A
b11 g
b11 l
b1 /
b1 7
b1 9
b1 C
b1 H
b1 O
b1 S
b1 W
b1 [
b1 _
b1111 &
b1111 @
b1 8
b1 1
b1 6
b1 m
b1 )
b1 j
b11100010 %
b11100010 J
b11100010 a
b11100010 b
b111100000001 (
b111100000001 >
b11 2
b11 ?
b11 F
b11 G
13
#12
03
b101000 4
b101000 e
#13
b101000 #
b101000 5
b101000 i
1T
0D
b10 h
b10 '
b10 B
b10 I
b10 $
b10 A
b10 g
b10 l
b11110110 /
b11110110 7
b11110110 9
b11110110 C
b11110110 H
b11110110 O
b11110110 S
b11110110 W
b11110110 [
b11110110 _
b110 &
b110 @
b11110110 8
b11001110 1
b11001110 6
b11001110 m
b11001110 )
b11001110 j
b11011001110 (
b11011001110 >
b1 2
b1 ?
b1 F
b1 G
13
#14
03
#15
b11110110 #
b11110110 5
b11110110 i
0T
1`
b1 h
b10000 '
b10000 B
b10000 I
b1 $
b1 A
b1 g
b1 l
b11110110 /
b11110110 7
b11110110 9
b11110110 C
b11110110 H
b11110110 O
b11110110 S
b11110110 W
b11110110 [
b11110110 _
b1100 &
b1100 @
b11110110 8
b0 1
b0 6
b0 m
b0 )
b0 j
b11110110 .
b11110110 M
b11110110 U
b11110110 V
b11110110 d
b110000000000 (
b110000000000 >
b10 2
b10 ?
b10 F
b10 G
13
#16
03
#17
b0 #
b0 5
b0 i
0`
1D
b11 h
b1000000 '
b1000000 B
b1000000 I
b11 $
b11 A
b11 g
b11 l
b1 /
b1 7
b1 9
b1 C
b1 H
b1 O
b1 S
b1 W
b1 [
b1 _
b1111 &
b1111 @
b1 8
b1 1
b1 6
b1 m
b1 )
b1 j
b11110110 %
b11110110 J
b11110110 a
b11110110 b
b111100000001 (
b111100000001 >
b11 2
b11 ?
b11 F
b11 G
13
#18
03
b111100 4
b111100 e
#19
1"
b111100 #
b111100 5
b111100 i
1T
0D
b10 h
b10 '
b10 B
b10 I
b10 $
b10 A
b10 g
b10 l
b1010 /
b1010 7
b1010 9
b1010 C
b1010 H
b1010 O
b1010 S
b1010 W
b1010 [
b1010 _
b110 &
b110 @
b100001010 8
b11001110 1
b11001110 6
b11001110 m
b11001110 )
b11001110 j
b11011001110 (
b11011001110 >
b1 2
b1 ?
b1 F
b1 G
13
#20
03
#21
b1010 #
b1010 5
b1010 i
0T
1`
b1 h
b10000 '
b10000 B
b10000 I
b1 $
b1 A
b1 g
b1 l
b1010 /
b1010 7
b1010 9
b1010 C
b1010 H
b1010 O
b1010 S
b1010 W
b1010 [
b1010 _
0"
b1100 &
b1100 @
b1010 8
b0 1
b0 6
b0 m
b0 )
b0 j
b1010 .
b1010 M
b1010 U
b1010 V
b1010 d
1+
b110000000000 (
b110000000000 >
b10 2
b10 ?
b10 F
b10 G
13
#22
03
#23
b0 #
b0 5
b0 i
0`
1D
b11 h
b1000000 '
b1000000 B
b1000000 I
b11 $
b11 A
b11 g
b11 l
b1 /
b1 7
b1 9
b1 C
b1 H
b1 O
b1 S
b1 W
b1 [
b1 _
b1111 &
b1111 @
b1 8
b1 1
b1 6
b1 m
b1 )
b1 j
0+
b1010 %
b1010 J
b1010 a
b1010 b
b111100000001 (
b111100000001 >
b11 2
b11 ?
b11 F
b11 G
13
#24
03
b1010000 4
b1010000 e
#25
1"
b1010000 #
b1010000 5
b1010000 i
1T
0D
b10 h
b10 '
b10 B
b10 I
b10 $
b10 A
b10 g
b10 l
b11110 /
b11110 7
b11110 9
b11110 C
b11110 H
b11110 O
b11110 S
b11110 W
b11110 [
b11110 _
b110 &
b110 @
b100011110 8
b11001110 1
b11001110 6
b11001110 m
b11001110 )
b11001110 j
b11011001110 (
b11011001110 >
b1 2
b1 ?
b1 F
b1 G
13
#26
03
#27
b11110 #
b11110 5
b11110 i
0T
1`
b1 h
b10000 '
b10000 B
b10000 I
b1 $
b1 A
b1 g
b1 l
b11110 /
b11110 7
b11110 9
b11110 C
b11110 H
b11110 O
b11110 S
b11110 W
b11110 [
b11110 _
0"
b1100 &
b1100 @
b11110 8
b0 1
b0 6
b0 m
b0 )
b0 j
1+
b11110 .
b11110 M
b11110 U
b11110 V
b11110 d
b110000000000 (
b110000000000 >
b10 2
b10 ?
b10 F
b10 G
13
#28
03
#29
b0 #
b0 5
b0 i
0`
1D
b11 h
b1000000 '
b1000000 B
b1000000 I
b11 $
b11 A
b11 g
b11 l
b1 /
b1 7
b1 9
b1 C
b1 H
b1 O
b1 S
b1 W
b1 [
b1 _
b1111 &
b1111 @
b1 8
b1 1
b1 6
b1 m
b1 )
b1 j
b11110 %
b11110 J
b11110 a
b11110 b
0+
b111100000001 (
b111100000001 >
b11 2
b11 ?
b11 F
b11 G
13
#30
03
b1100100 4
b1100100 e
#31
1"
b1100100 #
b1100100 5
b1100100 i
1T
0D
b10 h
b10 '
b10 B
b10 I
b10 $
b10 A
b10 g
b10 l
b110010 /
b110010 7
b110010 9
b110010 C
b110010 H
b110010 O
b110010 S
b110010 W
b110010 [
b110010 _
b110 &
b110 @
b100110010 8
b11001110 1
b11001110 6
b11001110 m
b11001110 )
b11001110 j
b11011001110 (
b11011001110 >
b1 2
b1 ?
b1 F
b1 G
13
#32
03
#33
b110010 #
b110010 5
b110010 i
0T
1`
b1 h
b10000 '
b10000 B
b10000 I
b1 $
b1 A
b1 g
b1 l
b110010 /
b110010 7
b110010 9
b110010 C
b110010 H
b110010 O
b110010 S
b110010 W
b110010 [
b110010 _
0"
b1100 &
b1100 @
b110010 8
b0 1
b0 6
b0 m
b0 )
b0 j
b110010 .
b110010 M
b110010 U
b110010 V
b110010 d
1+
b110000000000 (
b110000000000 >
b10 2
b10 ?
b10 F
b10 G
13
#34
03
#35
b0 #
b0 5
b0 i
0`
1D
b11 h
b1000000 '
b1000000 B
b1000000 I
b11 $
b11 A
b11 g
b11 l
b1 /
b1 7
b1 9
b1 C
b1 H
b1 O
b1 S
b1 W
b1 [
b1 _
b1111 &
b1111 @
b1 8
b1 1
b1 6
b1 m
b1 )
b1 j
0+
b110010 %
b110010 J
b110010 a
b110010 b
b111100000001 (
b111100000001 >
b11 2
b11 ?
b11 F
b11 G
13
#36
03
b1101110 4
b1101110 e
#37
1"
b1101110 #
b1101110 5
b1101110 i
1T
0D
b10 h
b10 '
b10 B
b10 I
b10 $
b10 A
b10 g
b10 l
b111100 /
b111100 7
b111100 9
b111100 C
b111100 H
b111100 O
b111100 S
b111100 W
b111100 [
b111100 _
b110 &
b110 @
b100111100 8
b11001110 1
b11001110 6
b11001110 m
b11001110 )
b11001110 j
b11011001110 (
b11011001110 >
b1 2
b1 ?
b1 F
b1 G
13
#38
03
#39
b111100 #
b111100 5
b111100 i
0T
1`
b1 h
b10000 '
b10000 B
b10000 I
b1 $
b1 A
b1 g
b1 l
b111100 /
b111100 7
b111100 9
b111100 C
b111100 H
b111100 O
b111100 S
b111100 W
b111100 [
b111100 _
0"
b1100 &
b1100 @
b111100 8
b0 1
b0 6
b0 m
b0 )
b0 j
1+
b111100 .
b111100 M
b111100 U
b111100 V
b111100 d
b110000000000 (
b110000000000 >
b10 2
b10 ?
b10 F
b10 G
13
#40
03
#41
b0 #
b0 5
b0 i
0`
1D
b11 h
b1000000 '
b1000000 B
b1000000 I
b11 $
b11 A
b11 g
b11 l
b1 /
b1 7
b1 9
b1 C
b1 H
b1 O
b1 S
b1 W
b1 [
b1 _
b1111 &
b1111 @
b1 8
b1 1
b1 6
b1 m
b1 )
b1 j
b111100 %
b111100 J
b111100 a
b111100 b
0+
b111100000001 (
b111100000001 >
b11 2
b11 ?
b11 F
b11 G
13
#42
03
b1011010 4
b1011010 e
#43
1"
b1011010 #
b1011010 5
b1011010 i
1T
0D
b10 h
b10 '
b10 B
b10 I
b10 $
b10 A
b10 g
b10 l
b101000 /
b101000 7
b101000 9
b101000 C
b101000 H
b101000 O
b101000 S
b101000 W
b101000 [
b101000 _
b110 &
b110 @
b100101000 8
b11001110 1
b11001110 6
b11001110 m
b11001110 )
b11001110 j
b11011001110 (
b11011001110 >
b1 2
b1 ?
b1 F
b1 G
13
#44
03
#45
b101000 #
b101000 5
b101000 i
0T
1`
b1 h
b10000 '
b10000 B
b10000 I
b1 $
b1 A
b1 g
b1 l
b101000 /
b101000 7
b101000 9
b101000 C
b101000 H
b101000 O
b101000 S
b101000 W
b101000 [
b101000 _
0"
b1100 &
b1100 @
b101000 8
b0 1
b0 6
b0 m
b0 )
b0 j
b101000 .
b101000 M
b101000 U
b101000 V
b101000 d
1+
b110000000000 (
b110000000000 >
b10 2
b10 ?
b10 F
b10 G
13
#46
03
#47
b0 #
b0 5
b0 i
0`
1D
b11 h
b1000000 '
b1000000 B
b1000000 I
b11 $
b11 A
b11 g
b11 l
b1 /
b1 7
b1 9
b1 C
b1 H
b1 O
b1 S
b1 W
b1 [
b1 _
b1111 &
b1111 @
b1 8
b1 1
b1 6
b1 m
b1 )
b1 j
0+
b101000 %
b101000 J
b101000 a
b101000 b
b111100000001 (
b111100000001 >
b11 2
b11 ?
b11 F
b11 G
13
#48
03
b1000110 4
b1000110 e
#49
1"
b1000110 #
b1000110 5
b1000110 i
1T
0D
b10 h
b10 '
b10 B
b10 I
b10 $
b10 A
b10 g
b10 l
b10100 /
b10100 7
b10100 9
b10100 C
b10100 H
b10100 O
b10100 S
b10100 W
b10100 [
b10100 _
b110 &
b110 @
b100010100 8
b11001110 1
b11001110 6
b11001110 m
b11001110 )
b11001110 j
b11011001110 (
b11011001110 >
b1 2
b1 ?
b1 F
b1 G
13
#50
03
#51
b10100 #
b10100 5
b10100 i
0T
1`
b1 h
b10000 '
b10000 B
b10000 I
b1 $
b1 A
b1 g
b1 l
b10100 /
b10100 7
b10100 9
b10100 C
b10100 H
b10100 O
b10100 S
b10100 W
b10100 [
b10100 _
0"
b1100 &
b1100 @
b10100 8
b0 1
b0 6
b0 m
b0 )
b0 j
1+
b10100 .
b10100 M
b10100 U
b10100 V
b10100 d
b110000000000 (
b110000000000 >
b10 2
b10 ?
b10 F
b10 G
13
#52
03
#53
b0 #
b0 5
b0 i
0`
1D
b11 h
b1000000 '
b1000000 B
b1000000 I
b11 $
b11 A
b11 g
b11 l
b1 /
b1 7
b1 9
b1 C
b1 H
b1 O
b1 S
b1 W
b1 [
b1 _
b1111 &
b1111 @
b1 8
b1 1
b1 6
b1 m
b1 )
b1 j
b10100 %
b10100 J
b10100 a
b10100 b
0+
b111100000001 (
b111100000001 >
b11 2
b11 ?
b11 F
b11 G
13
#54
03
b110010 4
b110010 e
#55
1"
b110010 #
b110010 5
b110010 i
1T
0D
b10 h
b10 '
b10 B
b10 I
b10 $
b10 A
b10 g
b10 l
b0 /
b0 7
b0 9
b0 C
b0 H
b0 O
b0 S
b0 W
b0 [
b0 _
b110 &
b110 @
b100000000 8
b11001110 1
b11001110 6
b11001110 m
b11001110 )
b11001110 j
b11011001110 (
b11011001110 >
b1 2
b1 ?
b1 F
b1 G
13
#56
03
#57
b0 #
b0 5
b0 i
0T
1`
b1 h
b10000 '
b10000 B
b10000 I
b1 $
b1 A
b1 g
b1 l
b0 /
b0 7
b0 9
b0 C
b0 H
b0 O
b0 S
b0 W
b0 [
b0 _
0"
b1100 &
b1100 @
b0 8
b0 1
b0 6
b0 m
b0 )
b0 j
b0 .
b0 M
b0 U
b0 V
b0 d
1+
b110000000000 (
b110000000000 >
b10 2
b10 ?
b10 F
b10 G
13
#58
03
#59
0`
1D
b11 h
b1000000 '
b1000000 B
b1000000 I
b11 $
b11 A
b11 g
b11 l
b1 /
b1 7
b1 9
b1 C
b1 H
b1 O
b1 S
b1 W
b1 [
b1 _
b1111 &
b1111 @
b1 8
b1 1
b1 6
b1 m
b1 )
b1 j
0+
b0 %
b0 J
b0 a
b0 b
b111100000001 (
b111100000001 >
b11 2
b11 ?
b11 F
b11 G
13
#60
03
b11110 4
b11110 e
#61
b11110 #
b11110 5
b11110 i
1T
0D
b10 h
b10 '
b10 B
b10 I
b10 $
b10 A
b10 g
b10 l
b11101100 /
b11101100 7
b11101100 9
b11101100 C
b11101100 H
b11101100 O
b11101100 S
b11101100 W
b11101100 [
b11101100 _
b110 &
b110 @
b11101100 8
b11001110 1
b11001110 6
b11001110 m
b11001110 )
b11001110 j
b11011001110 (
b11011001110 >
b1 2
b1 ?
b1 F
b1 G
13
#62
03
#63
b11101100 #
b11101100 5
b11101100 i
0T
1`
b1 h
b10000 '
b10000 B
b10000 I
b1 $
b1 A
b1 g
b1 l
b11101100 /
b11101100 7
b11101100 9
b11101100 C
b11101100 H
b11101100 O
b11101100 S
b11101100 W
b11101100 [
b11101100 _
b1100 &
b1100 @
b11101100 8
b0 1
b0 6
b0 m
b0 )
b0 j
b11101100 .
b11101100 M
b11101100 U
b11101100 V
b11101100 d
b110000000000 (
b110000000000 >
b10 2
b10 ?
b10 F
b10 G
13
#64
03
#65
b0 #
b0 5
b0 i
0`
1D
b11 h
b1000000 '
b1000000 B
b1000000 I
b11 $
b11 A
b11 g
b11 l
b1 /
b1 7
b1 9
b1 C
b1 H
b1 O
b1 S
b1 W
b1 [
b1 _
b1111 &
b1111 @
b1 8
b1 1
b1 6
b1 m
b1 )
b1 j
b11101100 %
b11101100 J
b11101100 a
b11101100 b
b111100000001 (
b111100000001 >
b11 2
b11 ?
b11 F
b11 G
13
#66
03
b10100 4
b10100 e
#67
b10100 #
b10100 5
b10100 i
1T
0D
b10 h
b10 '
b10 B
b10 I
b10 $
b10 A
b10 g
b10 l
b11100010 /
b11100010 7
b11100010 9
b11100010 C
b11100010 H
b11100010 O
b11100010 S
b11100010 W
b11100010 [
b11100010 _
b110 &
b110 @
b11100010 8
b11001110 1
b11001110 6
b11001110 m
b11001110 )
b11001110 j
b11011001110 (
b11011001110 >
b1 2
b1 ?
b1 F
b1 G
13
#68
03
#69
b11100010 #
b11100010 5
b11100010 i
0T
1`
b1 h
b10000 '
b10000 B
b10000 I
b1 $
b1 A
b1 g
b1 l
b11100010 /
b11100010 7
b11100010 9
b11100010 C
b11100010 H
b11100010 O
b11100010 S
b11100010 W
b11100010 [
b11100010 _
b1100 &
b1100 @
b11100010 8
b0 1
b0 6
b0 m
b0 )
b0 j
b11100010 .
b11100010 M
b11100010 U
b11100010 V
b11100010 d
b110000000000 (
b110000000000 >
b10 2
b10 ?
b10 F
b10 G
13
#70
03
#71
b0 #
b0 5
b0 i
0`
1D
b11 h
b1000000 '
b1000000 B
b1000000 I
b11 $
b11 A
b11 g
b11 l
b1 /
b1 7
b1 9
b1 C
b1 H
b1 O
b1 S
b1 W
b1 [
b1 _
b1111 &
b1111 @
b1 8
b1 1
b1 6
b1 m
b1 )
b1 j
b11100010 %
b11100010 J
b11100010 a
b11100010 b
b111100000001 (
b111100000001 >
b11 2
b11 ?
b11 F
b11 G
13
#72
03
b100011 4
b100011 e
