集積回路工学/#3_state_machine/Q2/calc.v
module calc(CLK, KEY, OP, EQUAL, CLR, EVENT, RESULT, STATE);
    input CLK;
    input [3:0] KEY;
    input OP, EQUAL, CLR, EVENT;
    output [7:0] RESULT;
    output [2:0] STATE;

    reg [3:0] value1, value2;
    reg op;
    reg [7:0] result;
    reg [2:0] state;

    always @(posedge CLK) begin
        if (CLR) begin
            state <= 3'd0;
            result <= 8'd0;
            op <= 0;
        end
        else begin
            case (state)
                3'd0: state <= (KEY && EVENT) ? 3'd1 : 3'd0;
                3'd1: state <= (EVENT) ? 3'd2 : 3'd1;
                3'd2: state <= (KEY && EVENT) ? 3'd3 : 3'd2;
                3'd3: state <= (EQUAL && EVENT) ? 3'd4 : 3'd3;
                3'd4: state <= (CLR && EVENT) ? 3'd0 : 3'd4;
            endcase

            value1 <= (state == 3'd0) ? KEY : value1;
            op <= (state == 3'd1) ? OP : op;
            value2 <= (state == 3'd2) ? KEY : value2;
            result <= (state == 3'd4 && op == 0) ? value1 + value2
                    : (state == 3'd4 && op == 1) ? value1 * value2
                    : RESULT;
        end
    end

    assign STATE = state;
    assign RESULT = result;

endmodule

集積回路工学/#3_state_machine/Q2/testbench.v
module testbench;
    reg CLK, CLR;
    reg [3:0] KEY;
    reg OP;
    reg EVENT, EQUAL;
    wire [7:0] RESULT;
    wire [2:0] STATE;

    initial
    begin
        $dumpfile("calc.vcd");
        $dumpvars(0, testbench);
        $monitor("CLK:%b CLR:%b KEY:%d OP:%b, EQUAL:%b, EVENT:%d, RESULT:%d, STATE:%d",
                  CLK, CLR, KEY, OP, EQUAL, EVENT, RESULT, STATE);
        CLK <= 0;
        CLR <= 0;
        KEY <= 0;
        OP <= 0;
        EVENT <= 0;
        EQUAL <= 0;

        #2
            CLR <= 1;
            EVENT <= 1;
        #2
            CLR <= 0;
            EVENT <= 0;

        // 4 + 5
        #4
            KEY <= 4'd4;
            EVENT <= 1;
        #2
            KEY <= 4'd0;
            EVENT <= 0;
        #4
            OP <= 0;
            EVENT <= 1;
        #2
            EVENT <= 0;
        #4
            KEY <= 4'd5;
            EVENT <= 1;
        #2
            KEY <= 4'd0;
            EVENT <= 0;
        #4
            EQUAL <= 1;
            EVENT <= 1;
        #2
            EQUAL <= 0;
            EVENT <= 0;
        #4
            CLR <= 1;
            EVENT <= 1;
        #2
            CLR <= 0;
            EVENT <= 0;

        // 9 * 8
        #4
            KEY <= 4'd9;
            EVENT <= 1;
        #2
            KEY <= 4'd0;
            EVENT <= 0;
        #4
            OP <= 1;
            EVENT <= 1;
        #2
            OP <= 0;
            EVENT <= 0;
        #4
            KEY <= 4'd8;
            EVENT <= 1;
        #2
            KEY <= 4'd0;
            EVENT <= 0;
        #4
            EQUAL <= 1;
            EVENT <= 1;
        #2
            EQUAL <= 0;
            EVENT <= 0;
        #4
            $finish;
    end

    always #1
        CLK <= ~CLK;

    calc calc_inst(CLK, KEY, OP, EQUAL, CLR, EVENT, RESULT, STATE);

endmodule

集積回路工学/#3_state_machine/Q2/calc.vcd
$date
	Tue Jul 20 23:14:23 2021
$end
$version
	Icarus Verilog
$end
$timescale
	1s
$end
$scope module testbench $end
$var wire 3 ! STATE [2:0] $end
$var wire 8 " RESULT [7:0] $end
$var reg 1 # CLK $end
$var reg 1 $ CLR $end
$var reg 1 % EQUAL $end
$var reg 1 & EVENT $end
$var reg 4 ' KEY [3:0] $end
$var reg 1 ( OP $end
$scope module calc_inst $end
$var wire 1 # CLK $end
$var wire 1 $ CLR $end
$var wire 1 % EQUAL $end
$var wire 1 & EVENT $end
$var wire 4 ) KEY [3:0] $end
$var wire 1 ( OP $end
$var wire 8 * RESULT [7:0] $end
$var wire 3 + STATE [2:0] $end
$var reg 1 , op $end
$var reg 8 - result [7:0] $end
$var reg 3 . state [2:0] $end
$var reg 4 / value1 [3:0] $end
$var reg 4 0 value2 [3:0] $end
$upscope $end
$upscope $end
$enddefinitions $end
#0
$dumpvars
bx 0
bx /
bx .
bx -
x,
bx +
bx *
b0 )
0(
b0 '
0&
0%
0$
0#
bx "
bx !
$end
#1
1#
#2
0#
1&
1$
#3
0,
b0 "
b0 *
b0 -
b0 !
b0 +
b0 .
1#
#4
0#
0&
0$
#5
b0 /
1#
#6
0#
#7
1#
#8
0#
1&
b100 '
b100 )
#9
b100 /
b1 !
b1 +
b1 .
1#
#10
0#
0&
b0 '
b0 )
#11
1#
#12
0#
#13
1#
#14
0#
1&
#15
b10 !
b10 +
b10 .
1#
#16
0#
0&
#17
b0 0
1#
#18
0#
#19
1#
#20
0#
1&
b101 '
b101 )
#21
b101 0
b11 !
b11 +
b11 .
1#
#22
0#
0&
b0 '
b0 )
#23
1#
#24
0#
#25
1#
#26
0#
1&
1%
#27
b100 !
b100 +
b100 .
1#
#28
0#
0&
0%
#29
b1001 "
b1001 *
b1001 -
1#
#30
0#
#31
1#
#32
0#
1&
1$
#33
b0 "
b0 *
b0 -
b0 !
b0 +
b0 .
1#
#34
0#
0&
0$
#35
b0 /
1#
#36
0#
#37
1#
#38
0#
1&
b1001 '
b1001 )
#39
b1001 /
b1 !
b1 +
b1 .
1#
#40
0#
0&
b0 '
b0 )
#41
1#
#42
0#
#43
1#
#44
0#
1&
1(
#45
1,
b10 !
b10 +
b10 .
1#
#46
0#
0&
0(
#47
b0 0
1#
#48
0#
#49
1#
#50
0#
1&
b1000 '
b1000 )
#51
b1000 0
b11 !
b11 +
b11 .
1#
#52
0#
0&
b0 '
b0 )
#53
1#
#54
0#
#55
1#
#56
0#
1&
1%
#57
b100 !
b100 +
b100 .
1#
#58
0#
0&
0%
#59
b1001000 "
b1001000 *
b1001000 -
1#
