集積回路工学/ch3/my_design.v
module my_design(F,A,B,C);
	input A,B,C;
	output F;
	wire w1,w2,w3,w4;
	assign w2 = A & C;
	assign w3 = w1 & B;
	assign w4 = A & B;
	assign w1 = ~C;
	assign F = w2 | w3 | w4;
endmodule

module testbench;
	reg a,b,c;
	wire f;

	initial
	begin
		$dumpfile("my_design.vcd");
		$dumpvars(0, testbench);

		$monitor("%t: a:%b b:%b c:%b f:%b", $time, a, b, c, f);
		a <= 0;
		b <= 0;
		c <= 0;
		#8
			$finish;
	end

	always #1
		a <= ~a;
	always #2
		b <= ~b;
	always #4
		c <= ~c;
	my_design inst0 (f,a,b,c);
endmodule

集積回路工学/ch3/my_design.vcd
$date
	Mon May 10 00:24:42 2021
$end
$version
	Icarus Verilog
$end
$timescale
	1s
$end
$scope module testbench $end
$var wire 1 ! f $end
$var reg 1 " a $end
$var reg 1 # b $end
$var reg 1 $ c $end
$scope module inst0 $end
$var wire 1 " A $end
$var wire 1 # B $end
$var wire 1 $ C $end
$var wire 1 ! F $end
$var wire 1 % w1 $end
$var wire 1 & w2 $end
$var wire 1 ' w3 $end
$var wire 1 ( w4 $end
$upscope $end
$upscope $end
$enddefinitions $end
#0
$dumpvars
0(
0'
0&
1%
0$
0#
0"
0!
$end
#1
1"
#2
1!
1'
0"
1#
#3
1(
1"
#4
0!
0'
0(
0%
0"
0#
1$
#5
1!
1&
1"
#6
0!
0&
0"
1#
#7
1!
1&
1(
1"
#8
0!
0(
0&
1%
0"
0#
0$
