集積システム工学/Memory_System_Design/sync_sram.v
`define DATA_BIT 8     // 8 bit
`define ADDRESS_BIT 4  // 16 word

module sync_sram(CK,
                 ADDR,
                 CS,
                 WE,
                 RDATA,
                 WDATA);
    // IO ports
    input CK, CS, WE;
    input [`ADDRESS_BIT-1:0] ADDR;
    input [`DATA_BIT-1:0] WDATA;
    output [`DATA_BIT-1:0] RDATA;

    reg [`DATA_BIT-1:0] mem [0:2**`ADDRESS_BIT-1];  // Memory array

    // Timing buffers
    reg [`ADDRESS_BIT-1:0] adr;
    reg we, cs;
    reg [`DATA_BIT-1:0] rdata, wdata;

    wire [`DATA_BIT-1:0] himp;  // High impedance wire


    // Sychronizing all the inputs with the clock
    always @(posedge CK)
    begin
        adr <= ADDR; cs <= CS;
        we  <= WE; wdata  <= WDATA;
    end

    always @(negedge CK)
    begin
        if (we && cs)
            mem[adr] <= wdata;
        rdata <= (cs) ? mem[adr] : himp;     // Read
    end

    assign RDATA = rdata;
    assign himp = 8'bzzzzzzzz; // High Impedance
endmodule

集積システム工学/Memory_System_Design/sync_sram_tb.v
module testbench;
    reg ck, we, cs;
    reg [`ADDRESS_BIT-1:0] addr;
    reg [`DATA_BIT-1:0] wdata;

    wire [`DATA_BIT-1:0] rdata;

    initial
    begin
        $dumpfile("sync_sram.vcd");
        $dumpvars(0, testbench);
        ck <= 0; we <= 1; cs <= 1;
        addr <= 15;
        wdata <= 0;
        #32
        we <= 0;
        #32
        cs <= 0;
        #4
        $finish;
    end

    sync_sram inst0(ck, addr, cs, we, rdata, wdata);

    always #1 ck <= ~ck;

    always @(negedge ck)
    begin
        addr <= addr + 1;
        wdata <= wdata - 1;
    end
endmodule

集積システム工学/Memory_System_Design/sync_sram.vcd
$date
	Wed Oct 20 23:04:37 2021
$end
$version
	Icarus Verilog
$end
$timescale
	1s
$end
$scope module testbench $end
$var wire 8 ! rdata [7:0] $end
$var reg 4 " addr [3:0] $end
$var reg 1 # ck $end
$var reg 1 $ cs $end
$var reg 8 % wdata [7:0] $end
$var reg 1 & we $end
$scope module inst0 $end
$var wire 4 ' ADDR [3:0] $end
$var wire 1 # CK $end
$var wire 1 $ CS $end
$var wire 8 ( RDATA [7:0] $end
$var wire 8 ) WDATA [7:0] $end
$var wire 1 & WE $end
$var wire 8 * himp [7:0] $end
$var reg 4 + adr [3:0] $end
$var reg 1 , cs $end
$var reg 8 - rdata [7:0] $end
$var reg 8 . wdata [7:0] $end
$var reg 1 / we $end
$upscope $end
$upscope $end
$enddefinitions $end
#0
$dumpvars
x/
bx .
bx -
x,
bx +
bz *
b11111111 )
bx (
b0 '
1&
b11111111 %
1$
0#
b0 "
bx !
$end
#1
b11111111 .
1/
1,
b0 +
1#
#2
b11111110 %
b11111110 )
b1 "
b1 '
0#
#3
b11111110 .
b1 +
1#
#4
b11111101 %
b11111101 )
b10 "
b10 '
0#
#5
b11111101 .
b10 +
1#
#6
b11111100 %
b11111100 )
b11 "
b11 '
0#
#7
b11111100 .
b11 +
1#
#8
b11111011 %
b11111011 )
b100 "
b100 '
0#
#9
b11111011 .
b100 +
1#
#10
b11111010 %
b11111010 )
b101 "
b101 '
0#
#11
b11111010 .
b101 +
1#
#12
b11111001 %
b11111001 )
b110 "
b110 '
0#
#13
b11111001 .
b110 +
1#
#14
b11111000 %
b11111000 )
b111 "
b111 '
0#
#15
b11111000 .
b111 +
1#
#16
b11110111 %
b11110111 )
b1000 "
b1000 '
0#
#17
b11110111 .
b1000 +
1#
#18
b11110110 %
b11110110 )
b1001 "
b1001 '
0#
#19
b11110110 .
b1001 +
1#
#20
b11110101 %
b11110101 )
b1010 "
b1010 '
0#
#21
b11110101 .
b1010 +
1#
#22
b11110100 %
b11110100 )
b1011 "
b1011 '
0#
#23
b11110100 .
b1011 +
1#
#24
b11110011 %
b11110011 )
b1100 "
b1100 '
0#
#25
b11110011 .
b1100 +
1#
#26
b11110010 %
b11110010 )
b1101 "
b1101 '
0#
#27
b11110010 .
b1101 +
1#
#28
b11110001 %
b11110001 )
b1110 "
b1110 '
0#
#29
b11110001 .
b1110 +
1#
#30
b11110000 %
b11110000 )
b1111 "
b1111 '
0#
#31
b11110000 .
b1111 +
1#
#32
b11101111 %
b11101111 )
b0 "
b0 '
0#
0&
#33
b11101111 .
0/
b0 +
1#
#34
b11101110 %
b11101110 )
b1 "
b1 '
b11111111 !
b11111111 (
b11111111 -
0#
#35
b11101110 .
b1 +
1#
#36
b11111110 !
b11111110 (
b11111110 -
b11101101 %
b11101101 )
b10 "
b10 '
0#
#37
b11101101 .
b10 +
1#
#38
b11101100 %
b11101100 )
b11 "
b11 '
b11111101 !
b11111101 (
b11111101 -
0#
#39
b11101100 .
b11 +
1#
#40
b11111100 !
b11111100 (
b11111100 -
b11101011 %
b11101011 )
b100 "
b100 '
0#
#41
b11101011 .
b100 +
1#
#42
b11101010 %
b11101010 )
b101 "
b101 '
b11111011 !
b11111011 (
b11111011 -
0#
#43
b11101010 .
b101 +
1#
#44
b11111010 !
b11111010 (
b11111010 -
b11101001 %
b11101001 )
b110 "
b110 '
0#
#45
b11101001 .
b110 +
1#
#46
b11101000 %
b11101000 )
b111 "
b111 '
b11111001 !
b11111001 (
b11111001 -
0#
#47
b11101000 .
b111 +
1#
#48
b11111000 !
b11111000 (
b11111000 -
b11100111 %
b11100111 )
b1000 "
b1000 '
0#
#49
b11100111 .
b1000 +
1#
#50
b11100110 %
b11100110 )
b1001 "
b1001 '
b11110111 !
b11110111 (
b11110111 -
0#
#51
b11100110 .
b1001 +
1#
#52
b11110110 !
b11110110 (
b11110110 -
b11100101 %
b11100101 )
b1010 "
b1010 '
0#
#53
b11100101 .
b1010 +
1#
#54
b11100100 %
b11100100 )
b1011 "
b1011 '
b11110101 !
b11110101 (
b11110101 -
0#
#55
b11100100 .
b1011 +
1#
#56
b11110100 !
b11110100 (
b11110100 -
b11100011 %
b11100011 )
b1100 "
b1100 '
0#
#57
b11100011 .
b1100 +
1#
#58
b11100010 %
b11100010 )
b1101 "
b1101 '
b11110011 !
b11110011 (
b11110011 -
0#
#59
b11100010 .
b1101 +
1#
#60
b11110010 !
b11110010 (
b11110010 -
b11100001 %
b11100001 )
b1110 "
b1110 '
0#
#61
b11100001 .
b1110 +
1#
#62
b11100000 %
b11100000 )
b1111 "
b1111 '
b11110001 !
b11110001 (
b11110001 -
0#
#63
b11100000 .
b1111 +
1#
#64
b11110000 !
b11110000 (
b11110000 -
b11011111 %
b11011111 )
b0 "
b0 '
0#
0$
#65
b11011111 .
0,
b0 +
1#
#66
b11011110 %
b11011110 )
b1 "
b1 '
bz !
bz (
bz -
0#
#67
b11011110 .
b1 +
1#
#68
b11011101 %
b11011101 )
b10 "
b10 '
0#
