集積回路工学/6bitCPU/src/dut.v
module adder_6bit(Y, IM, BUS, cFlag);
    input [5:0] Y, IM;
    output [5:0] BUS;
    output cFlag;
    wire [6:0] add;

    assign add = Y + IM;
    assign BUS = add[5:0];
    assign cFlag = add[6];
endmodule

module programCounter(CK, LD_PC, AD, OUT);
	input CK, LD_PC;
    input [5:0] AD;
    output [5:0] OUT;
    reg [5:0] q;
    initial q <= 6'd0;

    always @(posedge CK)
        q <= (LD_PC) ? AD : q + 6'd1;

    assign OUT = q;
endmodule

module register(CK, LD, BUS, OUT);
	input CK, LD;
    input [5:0] BUS;
    output [5:0] OUT;
    reg [5:0] q;
    initial q <= 6'd0;

    always @(posedge CK)
        if(LD)
            q <= BUS;

    assign OUT = q;
endmodule

module selector(C0, C1, C2, C3, S, Y);
	input [1:0] S;
    input [5:0] C0, C1, C2, C3;
    output [5:0] Y;

    assign Y = (S == 2'd0) ? C0 :
        (S == 2'd1) ? C1 :
        (S == 2'd2) ? C2 : C3;
endmodule

module registers(CK, LD_A, LD_B, LD_out, BUS, A_out, B_out, O_out);
	input CK, LD_A, LD_B, LD_out;
    input [5:0] BUS;
    output [5:0] A_out, B_out, O_out;

    register A_register (CK, LD_A, BUS, A_out);
    register B_register (CK, LD_B, BUS, B_out);
    register output_register (CK, LD_out, BUS, O_out);
endmodule

module decoder(LD_A, LD_B, LD_out, LD_PC, S, OP, Dcf);
	output LD_A, LD_B, LD_out, LD_PC;
	output [1:0] S;
	input [3:0] OP;
	input Dcf;

	reg [5:0] mem [0:26];

	assign LD_A = mem[{OP, Dcf}] >> 5;
	assign LD_B = mem[{OP, Dcf}] >> 4;
	assign LD_out = mem[{OP, Dcf}] >> 3;
	assign LD_PC = mem[{OP, Dcf}] >> 2;
	assign S = mem[{OP, Dcf}];

	// Micro Program
	initial begin
		mem[{4'b0000,1'b0}] <= {4'b0000, 2'b00};// NOP
		mem[{4'b0000,1'b1}] <= {4'b0000, 2'b00};
		mem[{4'b0001,1'b0}] <= {4'b1000, 2'b00};// ADD A, IM
		mem[{4'b0001,1'b1}] <= {4'b1000, 2'b00};
		mem[{4'b0010,1'b0}] <= {4'b1000, 2'b01};// MOV A, B + IM
		mem[{4'b0010,1'b1}] <= {4'b1000, 2'b01};
		mem[{4'b0011,1'b0}] <= {4'b1000, 2'b10};// IN A, in + IM
		mem[{4'b0011,1'b1}] <= {4'b1000, 2'b10};
		mem[{4'b0100,1'b0}] <= {4'b1000, 2'b11};// MOV A, IM
		mem[{4'b0100,1'b1}] <= {4'b1000, 2'b11};
		mem[{4'b0101,1'b0}] <= {4'b0100, 2'b00};// MOV B, A + IM
		mem[{4'b0101,1'b1}] <= {4'b0100, 2'b00};
		mem[{4'b0110,1'b0}] <= {4'b0100, 2'b01};// ADD B, IM
		mem[{4'b0110,1'b1}] <= {4'b0100, 2'b01};
		mem[{4'b0111,1'b0}] <= {4'b0100, 2'b10};// IN B, in + IM
		mem[{4'b0111,1'b1}] <= {4'b0100, 2'b10};
		mem[{4'b1000,1'b0}] <= {4'b0100, 2'b11};// MOV B, IM
		mem[{4'b1000,1'b1}] <= {4'b0100, 2'b11};
		mem[{4'b1001,1'b0}] <= {4'b0010, 2'b01};// OUT B + IM
		mem[{4'b1001,1'b1}] <= {4'b0010, 2'b01};
		mem[{4'b1010,1'b0}] <= {4'b0010, 2'b11};// OUT IM
		mem[{4'b1010,1'b1}] <= {4'b0010, 2'b11};
		mem[{4'b1011,1'b0}] <= {4'b0001, 2'b11};// JMP IM
		mem[{4'b1011,1'b1}] <= {4'b0001, 2'b11};
		mem[{4'b1100,1'b0}] <= {4'b0001, 2'b11};// JNC IM (JMP)
		mem[{4'b1100,1'b1}] <= {4'b0000, 2'b00};// JNC IM (NOP)
	end
endmodule

module ToyCPU_6bit(CK, in, Oout);
	input CK;
	input [5:0] in;
	output [5:0] Oout;

	wire [3:0] OP;
	wire [5:0] IM, Aout, Bout, BUS, Y, address;
	wire LD_A, LD_B, LD_out, LD_PC;
	wire [9:0] op_im;
	wire [1:0] S;
	wire cFlag;

	// pipeline registers
	reg [5:0] IF_IMreg, ID_IMreg, EX_BUSreg;
	reg [3:0] IF_OPreg;
	reg ID_LDAreg, ID_LDBreg, ID_LDoutreg, ID_LDPCreg, EX_LDAreg, EX_LDBreg, EX_LDoutreg, EX_LDPCreg;
	reg [1:0] ID_Sreg;

	// init pipeline registers
	initial begin
		IF_OPreg <= 0;
		IF_IMreg <= 0;
		ID_IMreg <= 0;
		EX_BUSreg <= 0;
		ID_Sreg <= 0;
		ID_LDAreg <= 0;
		ID_LDBreg <= 0;
		ID_LDoutreg <= 0;
		ID_LDPCreg <= 0;
		EX_LDAreg <= 0;
		EX_LDBreg <= 0;
		EX_LDoutreg <= 0;
		EX_LDPCreg <= 0;
	end

	// pipeline register update
	always @(posedge CK) begin
		IF_OPreg <= OP;
		IF_IMreg <= IM;
		ID_LDAreg <= LD_A;
		ID_LDBreg <= LD_B;
		ID_LDoutreg <= LD_out;
		ID_LDPCreg <= LD_PC;
		ID_Sreg <= S;
		ID_IMreg <= IF_IMreg;
		EX_BUSreg <= BUS;
		EX_LDAreg <= ID_LDAreg;
		EX_LDBreg <= ID_LDBreg;
		EX_LDoutreg <= ID_LDoutreg;
		EX_LDPCreg <= ID_LDPCreg;
	end

	rom_10bit_64word memory(address, op_im);

	assign IM = op_im; // neglect the top 6bits
	assign OP = (op_im >> 6);

	decoder decoder(LD_A, LD_B, LD_out, LD_PC, S, IF_OPreg, cFlag);
	selector selector(Aout, Bout, in, 6'd0, ID_Sreg, Y);
	adder_6bit alu(Y, ID_IMreg, BUS, cFlag);
	registers registers(CK, EX_LDAreg, EX_LDBreg, EX_LDoutreg, EX_BUSreg, Aout, Bout, Oout);
	programCounter programCounter(CK, EX_LDPCreg, EX_BUSreg, address);
endmodule

集積回路工学/6bitCPU/src/rom_10bit_64word.v
module rom_10bit_64word(AD,
                        Q);
    input [5:0] AD;
    output [9:0] Q;
    
    reg [9:0] q [0:63];
    
    initial begin
        // 課題1 (#12 P18) のプログラム
        // q[6'd0] <= {4'b0100, 6'd5};// MOV A, 5
        // q[6'd1] <= {4'b1000, 6'd10};// MOV B, 10
        
        // 課題2 (#12 P21) のプログラム
        // q[6'd0] <= {4'b0100, 6'd5};// MOV A, 5
        // q[6'd1] <= {4'b0000, 6'd0};// NOP
        // q[6'd2] <= {4'b0001, 6'd1};// NOP
        
        // 課題3 (#12 P25) のプログラム
        // q[6'd0] <= {4'b1011, 6'd5};
        // q[6'd1] <= {4'b0000, 6'd0};
        // q[6'd2] <= {4'b0000, 6'd0};
        // q[6'd3] <= {4'b0000, 6'd0};
        // q[6'd4] <= {4'b0100, 6'd4};
        // q[6'd5] <= {4'b1010, 6'd1};
        
        // 課題4 (#12 P26) のプログラム
        q[6'd0] <= {4'b0100, 6'd62};
        q[6'd1] <= {4'b0000, 6'd0};
        q[6'd2] <= {4'b0001, 6'd1};
        q[6'd3] <= {4'b1100, 6'd2};
        q[6'd4] <= {4'b0000, 6'd0};
        q[6'd5] <= {4'b0000, 6'd0};
        q[6'd6] <= {4'b0000, 6'd0};
    end
    
    assign Q = q[AD];
endmodule

集積回路工学/6bitCPU/src/testbench.v
module testbench;
	reg CK;
	reg [5:0] in;
	wire [5:0] Oout;

	initial begin
		$dumpfile("cpu.vcd");
		$dumpvars(0, testbench);
		CK <= 0;
		in <= 0;

		#40
			$finish;
	end

	always #1
		CK <= ~CK;

	ToyCPU_6bit ToyCPU_6bit(CK, in, Oout);
endmodule

集積回路工学/6bitCPU/src/cpu.vcd
$date
	Fri Jul 16 15:17:21 2021
$end
$version
	Icarus Verilog
$end
$timescale
	1s
$end
$scope module testbench $end
$var wire 6 ! Oout [5:0] $end
$var reg 1 " CK $end
$var reg 6 # in [5:0] $end
$scope module ToyCPU_6bit $end
$var wire 1 " CK $end
$var wire 6 $ in [5:0] $end
$var wire 10 % op_im [9:0] $end
$var wire 1 & cFlag $end
$var wire 6 ' address [5:0] $end
$var wire 6 ( Y [5:0] $end
$var wire 2 ) S [1:0] $end
$var wire 6 * Oout [5:0] $end
$var wire 4 + OP [3:0] $end
$var wire 1 , LD_out $end
$var wire 1 - LD_PC $end
$var wire 1 . LD_B $end
$var wire 1 / LD_A $end
$var wire 6 0 IM [5:0] $end
$var wire 6 1 Bout [5:0] $end
$var wire 6 2 BUS [5:0] $end
$var wire 6 3 Aout [5:0] $end
$var reg 6 4 EX_BUSreg [5:0] $end
$var reg 1 5 EX_LDAreg $end
$var reg 1 6 EX_LDBreg $end
$var reg 1 7 EX_LDPCreg $end
$var reg 1 8 EX_LDoutreg $end
$var reg 6 9 ID_IMreg [5:0] $end
$var reg 1 : ID_LDAreg $end
$var reg 1 ; ID_LDBreg $end
$var reg 1 < ID_LDPCreg $end
$var reg 1 = ID_LDoutreg $end
$var reg 2 > ID_Sreg [1:0] $end
$var reg 6 ? IF_IMreg [5:0] $end
$var reg 4 @ IF_OPreg [3:0] $end
$scope module alu $end
$var wire 6 A IM [5:0] $end
$var wire 1 & cFlag $end
$var wire 7 B add [6:0] $end
$var wire 6 C Y [5:0] $end
$var wire 6 D BUS [5:0] $end
$upscope $end
$scope module decoder $end
$var wire 1 & Dcf $end
$var wire 4 E OP [3:0] $end
$var wire 2 F S [1:0] $end
$var wire 1 , LD_out $end
$var wire 1 - LD_PC $end
$var wire 1 . LD_B $end
$var wire 1 / LD_A $end
$upscope $end
$scope module memory $end
$var wire 10 G Q [9:0] $end
$var wire 6 H AD [5:0] $end
$upscope $end
$scope module programCounter $end
$var wire 6 I AD [5:0] $end
$var wire 1 " CK $end
$var wire 1 7 LD_PC $end
$var wire 6 J OUT [5:0] $end
$var reg 6 K q [5:0] $end
$upscope $end
$scope module registers $end
$var wire 6 L BUS [5:0] $end
$var wire 1 " CK $end
$var wire 1 5 LD_A $end
$var wire 1 6 LD_B $end
$var wire 1 8 LD_out $end
$var wire 6 M O_out [5:0] $end
$var wire 6 N B_out [5:0] $end
$var wire 6 O A_out [5:0] $end
$scope module A_register $end
$var wire 6 P BUS [5:0] $end
$var wire 1 " CK $end
$var wire 1 5 LD $end
$var wire 6 Q OUT [5:0] $end
$var reg 6 R q [5:0] $end
$upscope $end
$scope module B_register $end
$var wire 6 S BUS [5:0] $end
$var wire 1 " CK $end
$var wire 1 6 LD $end
$var wire 6 T OUT [5:0] $end
$var reg 6 U q [5:0] $end
$upscope $end
$scope module output_register $end
$var wire 6 V BUS [5:0] $end
$var wire 1 " CK $end
$var wire 1 8 LD $end
$var wire 6 W OUT [5:0] $end
$var reg 6 X q [5:0] $end
$upscope $end
$upscope $end
$scope module selector $end
$var wire 6 Y C0 [5:0] $end
$var wire 6 Z C1 [5:0] $end
$var wire 6 [ C2 [5:0] $end
$var wire 6 \ C3 [5:0] $end
$var wire 2 ] S [1:0] $end
$var wire 6 ^ Y [5:0] $end
$upscope $end
$upscope $end
$upscope $end
$enddefinitions $end
#0
$dumpvars
b0 ^
b0 ]
b0 \
b0 [
b0 Z
b0 Y
b0 X
b0 W
b0 V
b0 U
b0 T
b0 S
b0 R
b0 Q
b0 P
b0 O
b0 N
b0 M
b0 L
b0 K
b0 J
b0 I
b0 H
b100111110 G
b0 F
b0 E
b0 D
b0 C
b0 B
b0 A
b0 @
b0 ?
b0 >
0=
0<
0;
0:
b0 9
08
07
06
05
b0 4
b0 3
b0 2
b0 1
b111110 0
0/
0.
0-
0,
b100 +
b0 *
b0 )
b0 (
b0 '
0&
b100111110 %
b0 $
b0 #
0"
b0 !
$end
#1
b0 +
1/
b0 0
b11 )
b11 F
b0 %
b0 G
b1 '
b1 H
b1 J
b1 K
b111110 ?
b100 @
b100 E
1"
#2
0"
#3
0/
b1 +
b111110 2
b111110 D
b0 )
b0 F
b1 0
b111110 B
b111110 9
b111110 A
b11 >
b11 ]
1:
b0 ?
b0 @
b0 E
b1000001 %
b1000001 G
b10 '
b10 H
b10 J
b10 K
1"
#4
0"
#5
b1100 +
1/
b10 0
b0 2
b0 D
b1100000010 %
b1100000010 G
b11 '
b11 H
b11 J
b11 K
15
b111110 4
b111110 I
b111110 L
b111110 P
b111110 S
b111110 V
b0 B
b0 9
b0 A
b0 >
b0 ]
0:
b1 ?
b1 @
b1 E
1"
#6
0"
#7
0/
1-
b0 +
b111111 2
b111111 D
b11 )
b11 F
b0 0
b111110 (
b111110 C
b111110 ^
05
b0 4
b0 I
b0 L
b0 P
b0 S
b0 V
b111111 B
b1 9
b1 A
1:
b10 ?
b1100 @
b1100 E
b0 %
b0 G
b100 '
b100 H
b100 J
b100 K
b111110 3
b111110 O
b111110 Q
b111110 R
b111110 Y
1"
#8
0"
#9
0-
b10 2
b10 D
b0 (
b0 C
b0 ^
b0 )
b0 F
b101 '
b101 H
b101 J
b101 K
15
b111111 4
b111111 I
b111111 L
b111111 P
b111111 S
b111111 V
b10 B
b10 9
b10 A
b11 >
b11 ]
1<
0:
b0 ?
b0 @
b0 E
1"
#10
0"
#11
b111111 2
b111111 D
b111111 (
b111111 C
b111111 ^
17
05
b10 4
b10 I
b10 L
b10 P
b10 S
b10 V
b111111 B
b0 9
b0 A
b0 >
b0 ]
0<
b110 '
b110 H
b110 J
b110 K
b111111 3
b111111 O
b111111 Q
b111111 R
b111111 Y
1"
#12
0"
#13
b1 +
b1 0
b1000001 %
b1000001 G
b10 '
b10 H
b10 J
b10 K
07
b111111 4
b111111 I
b111111 L
b111111 P
b111111 S
b111111 V
1"
#14
0"
#15
1/
b1100 +
b10 0
b1 ?
b1 @
b1 E
b1100000010 %
b1100000010 G
b11 '
b11 H
b11 J
b11 K
1"
#16
0"
#17
b0 +
0/
0-
b0 0
b0 2
b0 D
1&
b0 )
b0 F
b0 %
b0 G
b100 '
b100 H
b100 J
b100 K
b1000000 B
b1 9
b1 A
1:
b10 ?
b1100 @
b1100 E
1"
#18
0"
#19
b1 2
b1 D
15
b0 4
b0 I
b0 L
b0 P
b0 S
b0 V
b1000001 B
b10 9
b10 A
0:
b0 ?
b0 @
b0 E
b101 '
b101 H
b101 J
b101 K
1"
#20
0"
#21
b0 (
b0 C
b0 ^
b0 2
b0 D
0&
b0 3
b0 O
b0 Q
b0 R
b0 Y
b110 '
b110 H
b110 J
b110 K
05
b1 4
b1 I
b1 L
b1 P
b1 S
b1 V
b0 B
b0 9
b0 A
1"
#22
0"
#23
bx +
bx 0
b0 4
b0 I
b0 L
b0 P
b0 S
b0 V
bx %
bx G
b111 '
b111 H
b111 J
b111 K
1"
#24
0"
#25
x/
x.
x,
x-
bx )
bx F
b1000 '
b1000 H
b1000 J
b1000 K
bx ?
bx @
bx E
1"
#26
0"
#27
bx 2
bx D
x&
bx B
bx 9
bx A
bx >
bx ]
x<
x=
x;
x:
b1001 '
b1001 H
b1001 J
b1001 K
1"
#28
0"
#29
b1010 '
b1010 H
b1010 J
b1010 K
x7
x8
x6
x5
bx 4
bx I
bx L
bx P
bx S
bx V
1"
#30
0"
#31
bx '
bx H
bx J
bx K
1"
