集積回路工学/8bitCPU/src/dut.v
// Data Memory
module dm(dout, addr, BUS, LD, CK);
	output [7:0] dout;
	input [7:0] addr, BUS;
	input LD;
	input CK;
	reg [7:0] mem [0:255];
	integer i;

	initial begin
		for(i =0; i < 256; i = i + 1)
			mem[i] <= 8'd0;
	end

	always @(posedge CK) begin
		if(LD) begin
			mem[addr] <= BUS;
		end
	end

	assign dout = mem[addr];
endmodule




// Lookup Table (decoder)
module lut(LD, SEL, cFlag, OP);
	output [6:0] LD;
	output [2:0] SEL;
	input [4:0] OP;
	input cFlag;

	reg [9:0] mem [0:63];

	assign SEL = mem[{OP, cFlag}];
	assign LD = mem[{OP, cFlag}] >> 3;

	initial begin
		// 	   OP4-0   cFlag         LD6-0    SEL2-0
		mem[{5'b00000, 1'b0}] <= {7'b0000001, 3'b000};// ADD A, Im
		mem[{5'b00000, 1'b1}] <= {7'b0000001, 3'b000};
		mem[{5'b00001, 1'b0}] <= {7'b0000001, 3'b001};// MOV A, B + Im
		mem[{5'b00001, 1'b1}] <= {7'b0000001, 3'b001};
		mem[{5'b00010, 1'b0}] <= {7'b0000001, 3'b010};// IN A, in + Im
		mem[{5'b00010, 1'b1}] <= {7'b0000001, 3'b010};
		mem[{5'b00011, 1'b0}] <= {7'b0000001, 3'b011};// MOV A, Im
		mem[{5'b00011, 1'b1}] <= {7'b0000001, 3'b011};

		mem[{5'b00100, 1'b0}] <= {7'b0000010, 3'b000};// MOV B, A + Im
		mem[{5'b00100, 1'b1}] <= {7'b0000010, 3'b000};
		mem[{5'b00101, 1'b0}] <= {7'b0000010, 3'b001};// ADD B, Im
		mem[{5'b00101, 1'b1}] <= {7'b0000010, 3'b001};
		mem[{5'b00110, 1'b0}] <= {7'b0000010, 3'b010};// IN B, in + Im
		mem[{5'b00110, 1'b1}] <= {7'b0000010, 3'b010};
		mem[{5'b00111, 1'b0}] <= {7'b0000010, 3'b011};// MOV B, Im
		mem[{5'b00111, 1'b1}] <= {7'b0000010, 3'b011};

		mem[{5'b01000, 1'b0}] <= {7'b0000100, 3'b011};// MOV C, Im
		mem[{5'b01000, 1'b1}] <= {7'b0000100, 3'b011};
		mem[{5'b01001, 1'b0}] <= {7'b0001000, 3'b000};// MOV R[C], A + Im
		mem[{5'b01001, 1'b1}] <= {7'b0001000, 3'b000};
		mem[{5'b01010, 1'b0}] <= {7'b0000001, 3'b111};// MOV A, R[C]
		mem[{5'b01010, 1'b1}] <= {7'b0000001, 3'b111};
		mem[{5'b01011, 1'b0}] <= {7'b0000001, 3'b100};// ADD A, R[C]
		mem[{5'b01011, 1'b1}] <= {7'b0000001, 3'b100};

		mem[{5'b01100, 1'b0}] <= {7'b0010000, 3'b001};// OUT B + Im
		mem[{5'b01100, 1'b1}] <= {7'b0010000, 3'b001};
		mem[{5'b01101, 1'b0}] <= {7'b0010000, 3'b011};// OUT Im
		mem[{5'b01101, 1'b1}] <= {7'b0010000, 3'b011};

		mem[{5'b01110, 1'b0}] <= {7'b1000000, 3'b011};// JNC Im (JMP)
		mem[{5'b01110, 1'b1}] <= {7'b0000000, 3'b000};// JNC Im (NOP)

		mem[{5'b01111, 1'b0}] <= {7'b1000000, 3'b011};// JMP Im
		mem[{5'b01111, 1'b1}] <= {7'b1000000, 3'b011};

		mem[{5'b10000, 1'b0}] <= {7'b0100000, 3'b011};// MOV D, Im
		mem[{5'b10000, 1'b1}] <= {7'b0100000, 3'b011};
	end
endmodule




module program_counter_8b(AD, CK, LD, ADR, EVENT, VEC);
	output [7:0] AD;
	input [7:0] ADR, VEC;
	input CK, EVENT;
	input LD;

	reg [7:0] Q;

	initial begin
		Q <= 8'd0;
	end

	always @(posedge CK or posedge EVENT) begin
		if(EVENT && VEC != 8'd0) begin
			Q <= VEC;
		end else begin
			Q <= (LD) ? ADR : Q + 8'd1;
		end
	end

	assign AD = Q;
endmodule




module register_8b(QOUT, CK, LD, BUS);
	output [7:0] QOUT;
	input [7:0] BUS;
	input CK, LD;

	reg [7:0] Q;

	initial begin
		Q <= 8'd0;
	end

	always @(posedge CK) begin
		if(LD) begin
			Q <= BUS;
		end
	end

	assign QOUT = Q;
endmodule




module registers(Aout, Bout, Cout, Dout, Oout, CK, LD, BUS);
	output [7:0] Aout, Bout, Cout, Dout, Oout;
	input [7:0] BUS;
	input [6:0] LD;
	input CK;

	register_8b Areg(Aout, CK, LD[0], BUS);
	register_8b Breg(Bout, CK, LD[1], BUS);
	register_8b Creg(Cout, CK, LD[2], BUS);
	register_8b Dreg(Dout, CK, LD[5], BUS);
	register_8b Oreg(Oout, CK, LD[4], BUS);
endmodule




module sel1(Y, SEL, C0, C1, C2, C3);
	output [7:0] Y;
	input [7:0] C0, C1, C2, C3;
	input [2:0] SEL;

	wire [1:0] select;

	assign select = SEL;
	assign Y = (select == 2'd0) ? C0 :
			   (select == 2'd1) ? C1 :
			   (select == 2'd2) ? C2 : C3;
endmodule




module sel2(Y, SEL, C0, C1);
	output [7:0] Y;
	input [7:0] C0, C1;
	input [2:0] SEL;

	assign Y = (SEL[2] == 1'b0) ? C0 : C1;
endmodule




module alu(BUS, cFlag, Y, IM);
	output [7:0] BUS;
	output cFlag;
	input [7:0] Y, IM;
	wire [8:0] ADD;

	assign ADD = Y + IM;
	assign BUS = ADD;// connect the last 8 bits
	assign cFlag = ADD[8];
endmodule




module dff(D, CK, QOUT);
	input D, CK;
	output QOUT;

	reg Q;

	initial begin
		Q <= 1'd0;
	end

	always @(posedge CK) begin
		Q <= D;
	end

	assign QOUT = Q;
endmodule

集積回路工学/8bitCPU/Q3/im.v
// Instruction Memory
module im(dout,
          addr);
    output [12:0] dout;
    input [7:0] addr;
    
    reg [12:0] mem [0:255];
    
    initial begin
        mem[8'd0]  <= {5'b00011, 8'd0};
        mem[8'd1]  <= {5'b01000, 8'd0};
        mem[8'd2]  <= {5'b01001, 8'd0};
        mem[8'd3]  <= {5'b01000, 8'd1};
        mem[8'd4]  <= {5'b01001, 8'd0};
        mem[8'd5]  <= {5'b00011, 8'd1};
        mem[8'd6]  <= {5'b00100, 8'd0};
        mem[8'd7]  <= {5'b01100, 8'd0};
        mem[8'd8]  <= {5'b01001, 8'd0};
        mem[8'd9]  <= {5'b01000, 8'd0};
        mem[8'd10] <= {5'b01011, 8'd0};
        mem[8'd11] <= {5'b00100, 8'd0};
        mem[8'd12] <= {5'b01100, 8'd0};
        mem[8'd13] <= {5'b01001, 8'd0};
        mem[8'd14] <= {5'b01000, 8'd1};
        mem[8'd15] <= {5'b01011, 8'd0};
        mem[8'd16] <= {5'b00100, 8'd0};
        mem[8'd17] <= {5'b01100, 8'd0};
        mem[8'd18] <= {5'b01111, 8'd8};
    end
    
    assign dout = mem[addr];
endmodule

集積回路工学/8bitCPU/Q3/testbench.v
module testbench_cpu8;
	reg CK;
	wire [6:0] LD;
	wire [4:0] OP;
	wire [7:0] IM, Aout, Bout, Cout, Dout, Oout, BUS, Y, DMout, ADDR, ALU_IN;
	wire [12:0] IMout;
	wire cFlag, Dcflag;
	wire [2:0] SEL;
	wire key_event;

	reg [7:0] in;

	initial begin
		$dumpfile("cpu.vcd");
		$dumpvars(0, testbench_cpu8);

		CK <= 0;
		in <= 0;

		#200
			$finish;
	end

	always #1
		CK <= ~CK;

	assign key_event = 1'b0;// keypad
	registers registers(Aout, Bout, Cout, Dout, Oout, CK, LD, BUS);
	sel1 selector1(Y, SEL, Aout, Bout, in, 8'd0);
	alu alu(BUS, cFlag, Y, ALU_IN);
	dm data_memory(DMout, Cout, BUS, LD[3], CK);
	lut lut(LD, SEL, Dcflag, OP);
	im instruction_memory(IMout, ADDR);
	assign IM = IMout;// neglect the top 5 bits (OP)
	assign OP = (IMout >> 8);
	sel2 selector2(ALU_IN, SEL, IM, DMout);
	dff dff(cFlag, CK, Dcflag);
	program_counter_8b program_counter(ADDR, CK, LD[6], BUS, key_event, Dout);
endmodule

集積回路工学/8bitCPU/Q3/cpu.vcd
$date
	Fri Jul  9 16:11:56 2021
$end
$version
	Icarus Verilog
$end
$timescale
	1s
$end
$scope module testbench_cpu8 $end
$var wire 1 ! key_event $end
$var wire 1 " cFlag $end
$var wire 8 # Y [7:0] $end
$var wire 3 $ SEL [2:0] $end
$var wire 8 % Oout [7:0] $end
$var wire 5 & OP [4:0] $end
$var wire 7 ' LD [6:0] $end
$var wire 13 ( IMout [12:0] $end
$var wire 8 ) IM [7:0] $end
$var wire 8 * Dout [7:0] $end
$var wire 1 + Dcflag $end
$var wire 8 , DMout [7:0] $end
$var wire 8 - Cout [7:0] $end
$var wire 8 . Bout [7:0] $end
$var wire 8 / BUS [7:0] $end
$var wire 8 0 Aout [7:0] $end
$var wire 8 1 ALU_IN [7:0] $end
$var wire 8 2 ADDR [7:0] $end
$var reg 1 3 CK $end
$var reg 8 4 in [7:0] $end
$scope module alu $end
$var wire 1 " cFlag $end
$var wire 8 5 Y [7:0] $end
$var wire 8 6 IM [7:0] $end
$var wire 8 7 BUS [7:0] $end
$var wire 9 8 ADD [8:0] $end
$upscope $end
$scope module data_memory $end
$var wire 8 9 BUS [7:0] $end
$var wire 1 3 CK $end
$var wire 1 : LD $end
$var wire 8 ; dout [7:0] $end
$var wire 8 < addr [7:0] $end
$var integer 32 = i [31:0] $end
$upscope $end
$scope module dff $end
$var wire 1 3 CK $end
$var wire 1 " D $end
$var wire 1 + QOUT $end
$var reg 1 + Q $end
$upscope $end
$scope module instruction_memory $end
$var wire 13 > dout [12:0] $end
$var wire 8 ? addr [7:0] $end
$upscope $end
$scope module lut $end
$var wire 5 @ OP [4:0] $end
$var wire 1 + cFlag $end
$var wire 3 A SEL [2:0] $end
$var wire 7 B LD [6:0] $end
$upscope $end
$scope module program_counter $end
$var wire 8 C ADR [7:0] $end
$var wire 1 3 CK $end
$var wire 1 ! EVENT $end
$var wire 1 D LD $end
$var wire 8 E VEC [7:0] $end
$var wire 8 F AD [7:0] $end
$var reg 8 G Q [7:0] $end
$upscope $end
$scope module registers $end
$var wire 8 H BUS [7:0] $end
$var wire 1 3 CK $end
$var wire 7 I LD [6:0] $end
$var wire 8 J Oout [7:0] $end
$var wire 8 K Dout [7:0] $end
$var wire 8 L Cout [7:0] $end
$var wire 8 M Bout [7:0] $end
$var wire 8 N Aout [7:0] $end
$scope module Areg $end
$var wire 8 O BUS [7:0] $end
$var wire 1 3 CK $end
$var wire 1 P LD $end
$var wire 8 Q QOUT [7:0] $end
$var reg 8 R Q [7:0] $end
$upscope $end
$scope module Breg $end
$var wire 8 S BUS [7:0] $end
$var wire 1 3 CK $end
$var wire 1 T LD $end
$var wire 8 U QOUT [7:0] $end
$var reg 8 V Q [7:0] $end
$upscope $end
$scope module Creg $end
$var wire 8 W BUS [7:0] $end
$var wire 1 3 CK $end
$var wire 1 X LD $end
$var wire 8 Y QOUT [7:0] $end
$var reg 8 Z Q [7:0] $end
$upscope $end
$scope module Dreg $end
$var wire 8 [ BUS [7:0] $end
$var wire 1 3 CK $end
$var wire 1 \ LD $end
$var wire 8 ] QOUT [7:0] $end
$var reg 8 ^ Q [7:0] $end
$upscope $end
$scope module Oreg $end
$var wire 8 _ BUS [7:0] $end
$var wire 1 3 CK $end
$var wire 1 ` LD $end
$var wire 8 a QOUT [7:0] $end
$var reg 8 b Q [7:0] $end
$upscope $end
$upscope $end
$scope module selector1 $end
$var wire 8 c C0 [7:0] $end
$var wire 8 d C1 [7:0] $end
$var wire 8 e C2 [7:0] $end
$var wire 8 f C3 [7:0] $end
$var wire 3 g SEL [2:0] $end
$var wire 2 h select [1:0] $end
$var wire 8 i Y [7:0] $end
$upscope $end
$scope module selector2 $end
$var wire 8 j C0 [7:0] $end
$var wire 8 k C1 [7:0] $end
$var wire 3 l SEL [2:0] $end
$var wire 8 m Y [7:0] $end
$upscope $end
$upscope $end
$enddefinitions $end
#0
$dumpvars
b0 m
b11 l
b0 k
b0 j
b0 i
b11 h
b11 g
b0 f
b0 e
b0 d
b0 c
b0 b
b0 a
0`
b0 _
b0 ^
b0 ]
0\
b0 [
b0 Z
b0 Y
0X
b0 W
b0 V
b0 U
0T
b0 S
b0 R
b0 Q
1P
b0 O
b0 N
b0 M
b0 L
b0 K
b0 J
b1 I
b0 H
b0 G
b0 F
b0 E
0D
b0 C
b1 B
b11 A
b11 @
b0 ?
b1100000000 >
b100000000 =
b0 <
b0 ;
0:
b0 9
b0 8
b0 7
b0 6
b0 5
b0 4
03
b0 2
b0 1
b0 0
b0 /
b0 .
b0 -
b0 ,
0+
b0 *
b0 )
b1100000000 (
b1 '
b11 &
b0 %
b11 $
b0 #
0"
0!
$end
#1
0P
1X
b100 '
b100 B
b100 I
b1000 &
b1000 @
b100000000000 (
b100000000000 >
b1 2
b1 ?
b1 F
b1 G
13
#2
03
#3
0X
1:
b0 h
b1000 '
b1000 B
b1000 I
b0 $
b0 A
b0 g
b0 l
b1001 &
b1001 @
b100100000000 (
b100100000000 >
b10 2
b10 ?
b10 F
b10 G
13
#4
03
#5
1X
0:
b11 h
b100 '
b100 B
b100 I
b11 $
b11 A
b11 g
b11 l
b1 /
b1 7
b1 9
b1 C
b1 H
b1 O
b1 S
b1 W
b1 [
b1 _
b1000 &
b1000 @
b1 8
b1 1
b1 6
b1 m
b1 )
b1 j
b100000000001 (
b100000000001 >
b11 2
b11 ?
b11 F
b11 G
13
#6
03
#7
0X
1:
b0 h
b1000 '
b1000 B
b1000 I
b0 $
b0 A
b0 g
b0 l
b0 /
b0 7
b0 9
b0 C
b0 H
b0 O
b0 S
b0 W
b0 [
b0 _
b1001 &
b1001 @
b0 8
b0 1
b0 6
b0 m
b0 )
b0 j
b1 -
b1 <
b1 L
b1 Y
b1 Z
b100100000000 (
b100100000000 >
b100 2
b100 ?
b100 F
b100 G
13
#8
03
#9
1P
0:
b11 h
b1 '
b1 B
b1 I
b11 $
b11 A
b11 g
b11 l
b1 /
b1 7
b1 9
b1 C
b1 H
b1 O
b1 S
b1 W
b1 [
b1 _
b11 &
b11 @
b1 8
b1 1
b1 6
b1 m
b1 )
b1 j
b1100000001 (
b1100000001 >
b101 2
b101 ?
b101 F
b101 G
13
#10
03
#11
b1 #
b1 5
b1 i
0P
1T
b0 h
b10 '
b10 B
b10 I
b0 $
b0 A
b0 g
b0 l
b1 /
b1 7
b1 9
b1 C
b1 H
b1 O
b1 S
b1 W
b1 [
b1 _
b100 &
b100 @
b1 8
b0 1
b0 6
b0 m
b0 )
b0 j
b1 0
b1 N
b1 Q
b1 R
b1 c
b10000000000 (
b10000000000 >
b110 2
b110 ?
b110 F
b110 G
13
#12
03
#13
0T
1`
b1 h
b10000 '
b10000 B
b10000 I
b1 $
b1 A
b1 g
b1 l
b1100 &
b1100 @
b1 .
b1 M
b1 U
b1 V
b1 d
b110000000000 (
b110000000000 >
b111 2
b111 ?
b111 F
b111 G
13
#14
03
#15
0`
1:
b0 h
b1000 '
b1000 B
b1000 I
b0 $
b0 A
b0 g
b0 l
b1001 &
b1001 @
b1 %
b1 J
b1 a
b1 b
b100100000000 (
b100100000000 >
b1000 2
b1000 ?
b1000 F
b1000 G
13
#16
03
#17
b0 /
b0 7
b0 9
b0 C
b0 H
b0 O
b0 S
b0 W
b0 [
b0 _
b0 8
b0 #
b0 5
b0 i
1X
0:
b11 h
b100 '
b100 B
b100 I
b11 $
b11 A
b11 g
b11 l
b1000 &
b1000 @
b1 ,
b1 ;
b1 k
b100000000000 (
b100000000000 >
b1001 2
b1001 ?
b1001 F
b1001 G
13
#18
03
#19
b1 /
b1 7
b1 9
b1 C
b1 H
b1 O
b1 S
b1 W
b1 [
b1 _
b1 8
b1 #
b1 5
b1 i
1P
0X
b0 h
b1 '
b1 B
b1 I
b100 $
b100 A
b100 g
b100 l
b1011 &
b1011 @
b0 ,
b0 ;
b0 k
b0 -
b0 <
b0 L
b0 Y
b0 Z
b101100000000 (
b101100000000 >
b1010 2
b1010 ?
b1010 F
b1010 G
13
#20
03
#21
0P
1T
b10 '
b10 B
b10 I
b0 $
b0 A
b0 g
b0 l
b100 &
b100 @
b10000000000 (
b10000000000 >
b1011 2
b1011 ?
b1011 F
b1011 G
13
#22
03
#23
0T
1`
b1 h
b10000 '
b10000 B
b10000 I
b1 $
b1 A
b1 g
b1 l
b1100 &
b1100 @
b110000000000 (
b110000000000 >
b1100 2
b1100 ?
b1100 F
b1100 G
13
#24
03
#25
0`
1:
b0 h
b1000 '
b1000 B
b1000 I
b0 $
b0 A
b0 g
b0 l
b1001 &
b1001 @
b100100000000 (
b100100000000 >
b1101 2
b1101 ?
b1101 F
b1101 G
13
#26
03
#27
b0 #
b0 5
b0 i
1X
0:
b11 h
b100 '
b100 B
b100 I
b11 $
b11 A
b11 g
b11 l
b1 /
b1 7
b1 9
b1 C
b1 H
b1 O
b1 S
b1 W
b1 [
b1 _
b1000 &
b1000 @
b1 8
b1 1
b1 6
b1 m
b1 )
b1 j
b1 ,
b1 ;
b1 k
b100000000001 (
b100000000001 >
b1110 2
b1110 ?
b1110 F
b1110 G
13
#28
03
#29
b1 #
b1 5
b1 i
1P
0X
b0 h
b1 '
b1 B
b1 I
b100 $
b100 A
b100 g
b100 l
b10 /
b10 7
b10 9
b10 C
b10 H
b10 O
b10 S
b10 W
b10 [
b10 _
b1011 &
b1011 @
b10 8
b1 1
b1 6
b1 m
b0 )
b0 j
b1 -
b1 <
b1 L
b1 Y
b1 Z
b101100000000 (
b101100000000 >
b1111 2
b1111 ?
b1111 F
b1111 G
13
#30
03
#31
b0 1
b0 6
b0 m
0P
1T
b10 '
b10 B
b10 I
b0 $
b0 A
b0 g
b0 l
b10 /
b10 7
b10 9
b10 C
b10 H
b10 O
b10 S
b10 W
b10 [
b10 _
b100 &
b100 @
b10 8
b10 #
b10 5
b10 i
b10 0
b10 N
b10 Q
b10 R
b10 c
b10000000000 (
b10000000000 >
b10000 2
b10000 ?
b10000 F
b10000 G
13
#32
03
#33
0T
1`
b1 h
b10000 '
b10000 B
b10000 I
b1 $
b1 A
b1 g
b1 l
b1100 &
b1100 @
b10 .
b10 M
b10 U
b10 V
b10 d
b110000000000 (
b110000000000 >
b10001 2
b10001 ?
b10001 F
b10001 G
13
#34
03
#35
b0 #
b0 5
b0 i
0`
1D
b11 h
b1000000 '
b1000000 B
b1000000 I
b11 $
b11 A
b11 g
b11 l
b1000 /
b1000 7
b1000 9
b1000 C
b1000 H
b1000 O
b1000 S
b1000 W
b1000 [
b1000 _
b1111 &
b1111 @
b1000 8
b1000 1
b1000 6
b1000 m
b1000 )
b1000 j
b10 %
b10 J
b10 a
b10 b
b111100001000 (
b111100001000 >
b10010 2
b10010 ?
b10010 F
b10010 G
13
#36
03
#37
b10 #
b10 5
b10 i
0D
1:
b0 h
b1000 '
b1000 B
b1000 I
b0 $
b0 A
b0 g
b0 l
b10 /
b10 7
b10 9
b10 C
b10 H
b10 O
b10 S
b10 W
b10 [
b10 _
b1001 &
b1001 @
b10 8
b0 1
b0 6
b0 m
b0 )
b0 j
b100100000000 (
b100100000000 >
b1000 2
b1000 ?
b1000 F
b1000 G
13
#38
03
#39
b0 /
b0 7
b0 9
b0 C
b0 H
b0 O
b0 S
b0 W
b0 [
b0 _
b0 8
b0 #
b0 5
b0 i
1X
0:
b11 h
b100 '
b100 B
b100 I
b11 $
b11 A
b11 g
b11 l
b1000 &
b1000 @
b10 ,
b10 ;
b10 k
b100000000000 (
b100000000000 >
b1001 2
b1001 ?
b1001 F
b1001 G
13
#40
03
#41
b11 /
b11 7
b11 9
b11 C
b11 H
b11 O
b11 S
b11 W
b11 [
b11 _
b1 1
b1 6
b1 m
b11 8
b10 #
b10 5
b10 i
1P
0X
b0 h
b1 '
b1 B
b1 I
b100 $
b100 A
b100 g
b100 l
b1011 &
b1011 @
b1 ,
b1 ;
b1 k
b0 -
b0 <
b0 L
b0 Y
b0 Z
b101100000000 (
b101100000000 >
b1010 2
b1010 ?
b1010 F
b1010 G
13
#42
03
#43
b0 1
b0 6
b0 m
0P
1T
b10 '
b10 B
b10 I
b0 $
b0 A
b0 g
b0 l
b11 /
b11 7
b11 9
b11 C
b11 H
b11 O
b11 S
b11 W
b11 [
b11 _
b100 &
b100 @
b11 8
b11 #
b11 5
b11 i
b11 0
b11 N
b11 Q
b11 R
b11 c
b10000000000 (
b10000000000 >
b1011 2
b1011 ?
b1011 F
b1011 G
13
#44
03
#45
0T
1`
b1 h
b10000 '
b10000 B
b10000 I
b1 $
b1 A
b1 g
b1 l
b1100 &
b1100 @
b11 .
b11 M
b11 U
b11 V
b11 d
b110000000000 (
b110000000000 >
b1100 2
b1100 ?
b1100 F
b1100 G
13
#46
03
#47
0`
1:
b0 h
b1000 '
b1000 B
b1000 I
b0 $
b0 A
b0 g
b0 l
b1001 &
b1001 @
b11 %
b11 J
b11 a
b11 b
b100100000000 (
b100100000000 >
b1101 2
b1101 ?
b1101 F
b1101 G
13
#48
03
#49
b0 #
b0 5
b0 i
1X
0:
b11 h
b100 '
b100 B
b100 I
b11 $
b11 A
b11 g
b11 l
b1 /
b1 7
b1 9
b1 C
b1 H
b1 O
b1 S
b1 W
b1 [
b1 _
b1000 &
b1000 @
b1 8
b1 1
b1 6
b1 m
b1 )
b1 j
b11 ,
b11 ;
b11 k
b100000000001 (
b100000000001 >
b1110 2
b1110 ?
b1110 F
b1110 G
13
#50
03
#51
b11 #
b11 5
b11 i
1P
0X
b0 h
b1 '
b1 B
b1 I
b100 $
b100 A
b100 g
b100 l
b101 /
b101 7
b101 9
b101 C
b101 H
b101 O
b101 S
b101 W
b101 [
b101 _
b1011 &
b1011 @
b101 8
b10 1
b10 6
b10 m
b0 )
b0 j
b10 ,
b10 ;
b10 k
b1 -
b1 <
b1 L
b1 Y
b1 Z
b101100000000 (
b101100000000 >
b1111 2
b1111 ?
b1111 F
b1111 G
13
#52
03
#53
b0 1
b0 6
b0 m
0P
1T
b10 '
b10 B
b10 I
b0 $
b0 A
b0 g
b0 l
b101 /
b101 7
b101 9
b101 C
b101 H
b101 O
b101 S
b101 W
b101 [
b101 _
b100 &
b100 @
b101 8
b101 #
b101 5
b101 i
b101 0
b101 N
b101 Q
b101 R
b101 c
b10000000000 (
b10000000000 >
b10000 2
b10000 ?
b10000 F
b10000 G
13
#54
03
#55
0T
1`
b1 h
b10000 '
b10000 B
b10000 I
b1 $
b1 A
b1 g
b1 l
b1100 &
b1100 @
b101 .
b101 M
b101 U
b101 V
b101 d
b110000000000 (
b110000000000 >
b10001 2
b10001 ?
b10001 F
b10001 G
13
#56
03
#57
b0 #
b0 5
b0 i
0`
1D
b11 h
b1000000 '
b1000000 B
b1000000 I
b11 $
b11 A
b11 g
b11 l
b1000 /
b1000 7
b1000 9
b1000 C
b1000 H
b1000 O
b1000 S
b1000 W
b1000 [
b1000 _
b1111 &
b1111 @
b1000 8
b1000 1
b1000 6
b1000 m
b1000 )
b1000 j
b101 %
b101 J
b101 a
b101 b
b111100001000 (
b111100001000 >
b10010 2
b10010 ?
b10010 F
b10010 G
13
#58
03
#59
b101 #
b101 5
b101 i
0D
1:
b0 h
b1000 '
b1000 B
b1000 I
b0 $
b0 A
b0 g
b0 l
b101 /
b101 7
b101 9
b101 C
b101 H
b101 O
b101 S
b101 W
b101 [
b101 _
b1001 &
b1001 @
b101 8
b0 1
b0 6
b0 m
b0 )
b0 j
b100100000000 (
b100100000000 >
b1000 2
b1000 ?
b1000 F
b1000 G
13
#60
03
#61
b0 /
b0 7
b0 9
b0 C
b0 H
b0 O
b0 S
b0 W
b0 [
b0 _
b0 8
b0 #
b0 5
b0 i
1X
0:
b11 h
b100 '
b100 B
b100 I
b11 $
b11 A
b11 g
b11 l
b1000 &
b1000 @
b101 ,
b101 ;
b101 k
b100000000000 (
b100000000000 >
b1001 2
b1001 ?
b1001 F
b1001 G
13
#62
03
#63
b1000 /
b1000 7
b1000 9
b1000 C
b1000 H
b1000 O
b1000 S
b1000 W
b1000 [
b1000 _
b11 1
b11 6
b11 m
b1000 8
b101 #
b101 5
b101 i
1P
0X
b0 h
b1 '
b1 B
b1 I
b100 $
b100 A
b100 g
b100 l
b1011 &
b1011 @
b11 ,
b11 ;
b11 k
b0 -
b0 <
b0 L
b0 Y
b0 Z
b101100000000 (
b101100000000 >
b1010 2
b1010 ?
b1010 F
b1010 G
13
#64
03
#65
b0 1
b0 6
b0 m
0P
1T
b10 '
b10 B
b10 I
b0 $
b0 A
b0 g
b0 l
b1000 /
b1000 7
b1000 9
b1000 C
b1000 H
b1000 O
b1000 S
b1000 W
b1000 [
b1000 _
b100 &
b100 @
b1000 8
b1000 #
b1000 5
b1000 i
b1000 0
b1000 N
b1000 Q
b1000 R
b1000 c
b10000000000 (
b10000000000 >
b1011 2
b1011 ?
b1011 F
b1011 G
13
#66
03
#67
0T
1`
b1 h
b10000 '
b10000 B
b10000 I
b1 $
b1 A
b1 g
b1 l
b1100 &
b1100 @
b1000 .
b1000 M
b1000 U
b1000 V
b1000 d
b110000000000 (
b110000000000 >
b1100 2
b1100 ?
b1100 F
b1100 G
13
#68
03
#69
0`
1:
b0 h
b1000 '
b1000 B
b1000 I
b0 $
b0 A
b0 g
b0 l
b1001 &
b1001 @
b1000 %
b1000 J
b1000 a
b1000 b
b100100000000 (
b100100000000 >
b1101 2
b1101 ?
b1101 F
b1101 G
13
#70
03
#71
b0 #
b0 5
b0 i
1X
0:
b11 h
b100 '
b100 B
b100 I
b11 $
b11 A
b11 g
b11 l
b1 /
b1 7
b1 9
b1 C
b1 H
b1 O
b1 S
b1 W
b1 [
b1 _
b1000 &
b1000 @
b1 8
b1 1
b1 6
b1 m
b1 )
b1 j
b1000 ,
b1000 ;
b1000 k
b100000000001 (
b100000000001 >
b1110 2
b1110 ?
b1110 F
b1110 G
13
#72
03
#73
b1000 #
b1000 5
b1000 i
1P
0X
b0 h
b1 '
b1 B
b1 I
b100 $
b100 A
b100 g
b100 l
b1101 /
b1101 7
b1101 9
b1101 C
b1101 H
b1101 O
b1101 S
b1101 W
b1101 [
b1101 _
b1011 &
b1011 @
b1101 8
b101 1
b101 6
b101 m
b0 )
b0 j
b101 ,
b101 ;
b101 k
b1 -
b1 <
b1 L
b1 Y
b1 Z
b101100000000 (
b101100000000 >
b1111 2
b1111 ?
b1111 F
b1111 G
13
#74
03
#75
b0 1
b0 6
b0 m
0P
1T
b10 '
b10 B
b10 I
b0 $
b0 A
b0 g
b0 l
b1101 /
b1101 7
b1101 9
b1101 C
b1101 H
b1101 O
b1101 S
b1101 W
b1101 [
b1101 _
b100 &
b100 @
b1101 8
b1101 #
b1101 5
b1101 i
b1101 0
b1101 N
b1101 Q
b1101 R
b1101 c
b10000000000 (
b10000000000 >
b10000 2
b10000 ?
b10000 F
b10000 G
13
#76
03
#77
0T
1`
b1 h
b10000 '
b10000 B
b10000 I
b1 $
b1 A
b1 g
b1 l
b1100 &
b1100 @
b1101 .
b1101 M
b1101 U
b1101 V
b1101 d
b110000000000 (
b110000000000 >
b10001 2
b10001 ?
b10001 F
b10001 G
13
#78
03
#79
b0 #
b0 5
b0 i
0`
1D
b11 h
b1000000 '
b1000000 B
b1000000 I
b11 $
b11 A
b11 g
b11 l
b1000 /
b1000 7
b1000 9
b1000 C
b1000 H
b1000 O
b1000 S
b1000 W
b1000 [
b1000 _
b1111 &
b1111 @
b1000 8
b1000 1
b1000 6
b1000 m
b1000 )
b1000 j
b1101 %
b1101 J
b1101 a
b1101 b
b111100001000 (
b111100001000 >
b10010 2
b10010 ?
b10010 F
b10010 G
13
#80
03
#81
b1101 #
b1101 5
b1101 i
0D
1:
b0 h
b1000 '
b1000 B
b1000 I
b0 $
b0 A
b0 g
b0 l
b1101 /
b1101 7
b1101 9
b1101 C
b1101 H
b1101 O
b1101 S
b1101 W
b1101 [
b1101 _
b1001 &
b1001 @
b1101 8
b0 1
b0 6
b0 m
b0 )
b0 j
b100100000000 (
b100100000000 >
b1000 2
b1000 ?
b1000 F
b1000 G
13
#82
03
#83
b0 /
b0 7
b0 9
b0 C
b0 H
b0 O
b0 S
b0 W
b0 [
b0 _
b0 8
b0 #
b0 5
b0 i
1X
0:
b11 h
b100 '
b100 B
b100 I
b11 $
b11 A
b11 g
b11 l
b1000 &
b1000 @
b1101 ,
b1101 ;
b1101 k
b100000000000 (
b100000000000 >
b1001 2
b1001 ?
b1001 F
b1001 G
13
#84
03
#85
b10101 /
b10101 7
b10101 9
b10101 C
b10101 H
b10101 O
b10101 S
b10101 W
b10101 [
b10101 _
b1000 1
b1000 6
b1000 m
b10101 8
b1101 #
b1101 5
b1101 i
1P
0X
b0 h
b1 '
b1 B
b1 I
b100 $
b100 A
b100 g
b100 l
b1011 &
b1011 @
b1000 ,
b1000 ;
b1000 k
b0 -
b0 <
b0 L
b0 Y
b0 Z
b101100000000 (
b101100000000 >
b1010 2
b1010 ?
b1010 F
b1010 G
13
#86
03
#87
b0 1
b0 6
b0 m
0P
1T
b10 '
b10 B
b10 I
b0 $
b0 A
b0 g
b0 l
b10101 /
b10101 7
b10101 9
b10101 C
b10101 H
b10101 O
b10101 S
b10101 W
b10101 [
b10101 _
b100 &
b100 @
b10101 8
b10101 #
b10101 5
b10101 i
b10101 0
b10101 N
b10101 Q
b10101 R
b10101 c
b10000000000 (
b10000000000 >
b1011 2
b1011 ?
b1011 F
b1011 G
13
#88
03
#89
0T
1`
b1 h
b10000 '
b10000 B
b10000 I
b1 $
b1 A
b1 g
b1 l
b1100 &
b1100 @
b10101 .
b10101 M
b10101 U
b10101 V
b10101 d
b110000000000 (
b110000000000 >
b1100 2
b1100 ?
b1100 F
b1100 G
13
#90
03
